{
  "설정": {
    "문법": [
        "주어-동사",
        "주어-동사-목적어"
      ]
  },
  "대명사": {
    "1": {
      "ca": "나 (1인칭 단수)",
      "caj": "우리 (1인칭 복수)"
    },
    "2": {
      "ce": "너 (2인칭 단수)",
      "cej": "너희들 (2인칭 복수)"
    },
    "3": {
      "te": "그 (3인칭 남성)",
      "be": "그녀 (3인칭 여성 단수)",
      "ke": "그것 (사물 단수)",
      "tej": "그들 (3인칭 복수)"
    },
    "이외": {
      "kibe": "이것",
      "kibej": "이것들",
      "lebe": "저것",
      "lebej": "저것들"
    }
  },
  "조동사": {
    "trni": "~할 수 있다",
    "jnni": "~하는 것이 좋겠다.",
    "krni": "~해야 한다",
    "mni": {
      "뜻": "~이다",
      "변형": {
        "nmni": "~하고 있다.",
        "tmni": "당하다/되다."
      }
    },
    "vni": {
      "뜻": "~하다",
      "변형": {
        "vnid": {
          "뜻": "~했다",
          "예시": "(동사나 형용사가 없는 경우 사용)(동사/형용사가 있는 경우, 동사/형용사의 과거형 사용.)"
        },
        "vnif": {
          "뜻": "~할 것이다",
          "예시": "(동사나 형용사가 없는 경우. (동사/형용사가 있는 경우, 동사/형용사의 미래형 사용.)"
        }
      },
      "예시": "(동사나 형용사가 없는 경우에만 이렇게 사용한다.)"
    },
    "gni": {
      "뜻": "하고 싶다/원하다",
      "변형": {
        "gnid": "하고 싶었다"
      }
    }
  },
  "인사/감탄사": {
    "jorte": "안녕하세요(만날 때)",
    "snte": "안녕하세요(헤어질 때)",
    "onnol": "미안",
    "tetle": "고마워"
  },
  "접사": {
    "el-": "행위자.",
    "e-": "행위를 당하는 자",
    "th-": "도구/물건",
    "mu-": "장소",

    "vl'-": {
      "뜻":"형용사화",
      "변형": {
        "vl'-": "-한",
        "ivl'-": "-적"
      }
    },
    "yl'-": "부사화",
    "-t": "기본 부사",

    "a-": "동사를 명사화",
    "-us": "기본 명사",
    "-zi": "-주의",

    "-'j": "소유격 (~의)",
    "-'n": "서술 조사 (~은/는)",
    "-'t": "주격 (이/가)",
    "-'c": "목적어 (을/를)"
  },
  "연결어미 및 구성요소": {
    "kibom": {
      "뜻": "그리고"
    },
    "fesiem": {
      "뜻": "그러면"
    },
    "lisacm": {
      "뜻": "하지만"
    },
    "daisucm": {
      "뜻": "-아니/때문에"
    },
    "beim": {
      "뜻": "~에게"
    },
    "kwfom": {
      "뜻": "~으로"
    },
    "gupem": {
      "뜻": "~에서"
    }
  },
  "수사/계산": {
    "숫자": {
      "계산법": {
        "예시": "3234 = jasl jiteg kil jitag jasjig jal (3 * 1000 + 2 * 100 + 30 + 4)"
      },
      "0": "neol",
      "1": "kifl",
      "2": "kil",
      "3": "jasl",
      "4": "jal",
      "5": "kol",
      "6": "kiudl",
      "7": "mifl",
      "8": "qafl",
      "9": "dul",
      "10": {
        "10":"jig",
        "20": "kifjig",
        "30": "jasjig",
        "40": "jaljig",
        "50": "koljig",
        "60": "kiujig",
        "70": "mifjig",
        "80": "qafjig",
        "90": "duljig"
      },
      "100": "jitag",
      "1000": "jiteg",
      "10000": "jizag",
      "100000": "jizeg",
      "1000000": "jisag",
      "10000000": "jiseg",
      "100000000": "jihag"
    },
    "+ (더하기)": "dejjeisus",
    "/ (나누기)": "cacujsus",
    "* (곱셈) ": "dogsus",
    " - (빼기)": "gedisus",
    "=": "mni akenf (이다. 동일)"
  },
  "기본명사": {
    "gufus": "불",
    "tafebus": "흙",
    "sufus": "물",
    "gafaus": "바람",
    "gecbaius": "번개",
    "jacus": "산",
    "tacefus": "하늘",
    "bakus": "강",
    "crnsufus": "바다",
    "vknsufus": "호수",
    "jafaus": {"뜻":"사람", "변형": {"ivl'jafaus": "인간적"}},
    "jibacus": "시간",
    "kedus": "어둠",
    "gimus": "빛",
    "casus": "나무",
    "siekjekus": "명성",
    "laifious": "재료",
    "subeius": "무게",
    "basdokus": {"뜻":"감동", "변형": {"ivl'basdokus": "감동적"}},
    "balobus": "가족",
    "guckuibius": "분위기",
    "kiektiakus": "영향",
    "boakikus": "과잉",
    "bitoius": "기회",
    "jifleius": {"뜻":"실제", "변형": {"ivl'jifleius": "현실적"}},
    "tiebsiekus": {"뜻":"혁명", "변형": {"tiebsiekusiv": "혁명적"}},
    "lakgius": "장비",
    "jeigus": {"뜻":"세부", "변형": {"ivl'jeigus": "세부적"}},
    "geslus": "범주",
    "sejicus": {"뜻":"기계", "변형": {"ivl'sejicus": "기계적"}},
    "sidkwsus": "믿음",
    "dokfious": "동료",
    "daiqijous": "대피소",
    "lefmaus": "절차",
    "kiobwsus": "요금",
    "jifiebus": "시력",
    "qukbiekus": "풍경",
    "lecfiabus": {"뜻":"전략","변형":{"ivl'lecfiabus": "전략적"}},
    "gotesus": "보험",
    "qiosiecus": {"뜻":"표면","변형":{"ivl'qiosiecus": "표면적"}},
    "jeckisus": "선임",
    "mekjociecus": "청소년",
    "bwbdacus": {"뜻":"극단","변형": {"ivl'bwbdacus": "극단적"}},
    "qobfiebus": {"뜻":"폭력","변형": {"ivl'qobfiebus": "폭력적"}},
    "bieibius": "계기",
    "labwsus": "자금",
    "joctaius": "손해",
    "kifboaus": "일과",
    "bamius": "가치",
    "laicacus": "재난",
    "dosakus": "도망",
    "lafious": "자료",
    "gakgegus": "방법",
    "tisus": "힘",
    "jekgucus": "성분",
    "lagkifus": "잡일",
    "guqusus": "부품",
    "kieigiqusus": "예비품",
    "bieclebus": "견적",
    "bilucus": "기준",
    "taslekus": "함정",
    "bifus": "길",
    "befius": "거리",
    "jekbiebus": "성격",
    "bwckuecus": "근원",
    "daidajuus": "대다수",
    "gujeus": "부서",
    "laijacus": "재산",
    "jeidaius": "세대",
    "leflekus": "절정",
    "kilesus": "이점",
    "biuctiekus": "균형",
    "kulus": "우주",
    "jekboaus": "성과",
    "boaclesus": "관점",
    "cokjacsufus": "농산물",
    "likuecus": "지원",
    "toacjwkus": "환승",
    "cwkfiebus": "능력",
    "koibacus": "외간",
    "jakkicus": "상인",
    "lusicus": "주민",
    "babdous": "각도",
    "daifikicus": "대리인",
    "daikacus": "대안",
    "beblekus": "걱정",
    "kuibius": "위기",
    "toifous": "회로",
    "jaktoakus": "상황",
    "dwkbaus": "등가",
    "jicmasus": "신참",
    "jickiokus": "신용",
    "kiekpous": "영토",
    "guckiaus": "분야",
    "kucsiekus": "운명",
    "kigsuclaus": "입문자",
    "kikibus": "이익",
    "tieipaibus": "혜택",
    "tokjus": "홍수",
    "gakjibus": "방식",
    "jekgiefus": "성별",
    "moijous": "최소",
    "moidaius": "최대",
    "jecpaiblius": "선택지",
    "kwibiecus": "의견",
    "loaqious": "좌표",
    "gugucus": "부분",
    "gikiufus": "비율",
    "boakpaibus": "광택",
    "lecsucbaus": "전문가",
    "tiecjakus": "현상",
    "laslaifiebus": "잠재력",
    "lajeius": "자세",
    "soblebus": "목적",
    "toctagus": "혼합",
    "bieibwgus": "계급",
    "mwbsiecus": "측면",
    "bacwkjekus": "가능성",
    "goccwkus": "본능",
    "kieijius": "예시",
    "lakkaisufus": "장애물",
    "sabubacus": "마구간",
    "tabtoius": "학회",
    "daikiokqusus": "대용품",
    "bopokus": "고통",
    "dobus": "도구",
    "pwbjekus": "특성",
    "biciesqusus": "기념품",
    "baikicus": "개인",
    "kieflekus": "열정",
    "tobijisus": "호기심",
    "gufkacbasus": "불안감",
    "tablaus": "학자",
    "libkegus": "직업",
    "biojus": "교수",
    "biekfiebus": "경력",
    "litiekus": "지형",
    "labieblwkus": "자격증",
    "kiskuecus": "임원",
    "giectojaus": "변호사",
    "bakkwius": "강의",
    "poktabus": "통학",
    "biopokus": "교통",
    "jwkbaibus": "승객",
    "jajaiktoafus": "사생활",
    "jabous": "사고",
    "sakus": "망",
    "kiecfious": "연료",
    "ladokmaus": "자동차",
    "gotaiklaus": "보행자",
    "takbokjaus": "항공사",
    "gokpus": "봉투",
    "pafbejus": "탈것",
    "daifiubus": "대륙",
    "cokkegus": "농업",
    "taikacus": "해안",
    "cokkiabus": "농약",
    "kiubimeius": "유기체",
    "lagmous": "잡초",
    "leibubus": "제국",
    "koakbubus": "왕국",
    "baimeblaus": "개척자",
    "bubbiekus": "국경",
    "bodaius": "고대",
    "buckicus": "군인",
    "subius": "무기",
    "toasuffitabus": "양자역학",
    "gisiekus": "비명",
    "lisus": "짐",
    "buclukus": "군중",
    "kicfius": "인류",
    "pwbbuecus": "특권",
    "jekliblaus": "성직자",
    "biboacus": "기관",
    "kiclokus": "인종",
    "sucsaibus": "문맥",
    "becmubsufus": "건축물",
    "boacbaibus": "관객",
    "labqusus": "작품",
    "luleius": "주제",
    "jikicus": "시인",
    "jictoaus": "신화",
    "lufbefius": "줄거리",
    "toasiecus": "화면",
    "becmubtabus": "건축학",
    "jojefus": "소설",
    "bwckiubus": "근육",
    "lakbius": "장기(내장)",
    "jakmeus": "상처",
    "lifgiekus": "질병",
    "dobius": "독",
    "lufwsus": "주름",
    "jeiqous": "세포",
    "dacgaiblifus": "단백질",
    "toaclaus": "환자",
    "lwkjakus": "증상",
    "kasus": "암",
    "kiekkiakus": "영양",
    "jotoaus": "소화",
    "jicbiekus": "신경",
    "kaibmeius": "액체",
    "lecbius": "전기",
    "bakmefus": "강철",
    "suflifus": "물질",
    "lakuecus": "자원",
    "mefus": "철",
    "dafisius": "다리미",
    "guclaus": "분자",
    "jacjekus": "산성",
    "kiulecus": "유전",
    "kiuleclaus": "유전자",
    "bajefus": "가설",
    "jebpacus": "석탄",
    "kuecjous": "원소",
    "kiglaus": "입자",
    "bomeius": "고체",
    "bosus": "고무",
    "jacjous": "산소",
    "pacjous": "탄소",
    "desgufus": "덤불",
    "doksus": "동물",
    "lufbius": "줄기",
    "basusus": "가뭄",
    "jejibjius": "서식시",
    "toajebus": "화석",
    "jaikpaibieius": "생태계",
    "bitus": "기후",
    "kocdous": "온도",
    "jjikajus": "씨앗",
    "ggufius": "뿌리",
    "jjwfeibius": "쓰레기",
    "baikufus": "개울",
    "taimukus": "해충",
    "bocmukus": "곤충",
    "lilicus": "지진",
    "jasabus": "사막", 
    "jisicus": "시민",
    "bubsicus": "국민",
    "jodwbus": "소득",
    "leidous": "제도",
    "siclulukwius": "민주주의",
    "gikiokus": "비용",
    "gesloius": "범죄",
    "qitailaus": "피해자",
    "tabwglaus": "하급자",
    "jakboacus": "상관",
    "leclaus": "전자",
    "tulaus": "후자",
    "mecsuctablaus": "천문학자",
    "paidous": "태도",
    "lekdous": "정도",
    "ggiedaius": "뼈대",
    "lebkwius": "적의",
    "keksakus": "엉망",
    "tocfacus": "혼란",
    "tocdocus": "혼돈",
    "dacbieius": "단계",
    "jibieius": "시계",
    "sabdaibius": "막대기",
    "kicbius": "인기",
    "kuecfius": "원리",
    "quslifus": "품질",
    "likiebus": "지역",
    "lokbious": "종교",
    "lobabjakus": "조각상",
    "jakpaius": "상태",
    "lakjous": "장소",
    "tiubaus": "휴가",
    "jasiekbasus": "사명감",
    "giecjus": "변수",
    "kiofijaus": "요리사",
    "lufus": "줄",
    "sufmeius": "물체",
    "toijaus": "회사",
    "lukjislius": "중심지",
    "qukjwgus": "풍습",
    "jujlaus": "숫자",
    "kicsufus": "인물",
    "sojwgus": "모습",
    "kikius": "이유",
    "laiklesus": "쟁점",
    "sious": "묘",
    "baklesus": "강점",
    "jekciakus": "성냥",
    "jitagus": "시합",
    "qiekkuecus": "평원",
    "kaqapwus": "아파트",
    "jijefus": "시설",
    "cocsucus": "논문",
    "laglius": "잡지",
    "liqieius": "지폐",
    "doklecus": "동전",
    "golobwusus": "보조금",
    "bosius": "곰",
    "kaibjus": "액수",
    "gablaus": "박자",
    "gaikiebus": "배역",
    "gefbwsus": "벌금",
    "lujous": "주소",
    "lotakus": "조항",
    "saimeius": "매체",
    "pijius": "티슈",
    "kilaus": "이자",
    "bioboaus": "교과",
    "suclakus": "문장",
    "dackeus": "단어",
    "jufligus": "술집",
    "lekufus": "저울",
    "bokkieius": "공예",
    "kulujecus": "우주선",
    "jutabus": {"뜻":"수학","변형":{"ivl'jutabus": "수학적"}},
    "biumibus": {"뜻":"규칙","변형": {"ivl'biumibus": "규칙적인"}},   
    "jajakus": "사상",
    "boatabus": {"뜻": "과학","변형": {"ivl'boatabus": "과학적"}},
    "bijufus": {"뜻": "기술","변형": {"ivl'bijufus": "기술적"}},
    "lobecus": {"뜻": "조건","변형": {"ivl'lobecus": "조건적"}},
    "taikdokus": {"뜻": "행동","변형": {"ivl'taikdokus": "행동적"}},
    "jucjeus": {"뜻": "순서","변형": {"ivl'jucjeus": "순서적"}},
    "lukdobus": {"뜻": "중독","변형": {"ivl'lukdobus": "중독적"}},
    "jackegus": {"뜻": "산업","변형": {"ivl'jackegus": "산업적"}},
    "lecjefus": {"뜻": "전설","변형": {"ivl'lecjefus": "전설적"}},
    "suctabus": {"뜻": "문학","변형": {"ivl'suctabus": "문학적"}},
    "qiecbiecus": {"뜻": "편견","변형": {"ivl'qiecbiecus": "편견적"}},
    "ligdacus": {"뜻": "집단","변형": {"ivl'ligdacus": "집단적"}},
    "toabfiufus": {"뜻": "확률","변형": {"ivl'toabfiufus": "확률적"}},
    "kiebjaus": {"뜻": "역사","변형": {"ivl'kiebjasus": "역사적"}},
    "meftabus": {"뜻": "철학","변형": {"ivl'meftabus": "철학적"}},
    "biekleitabus": {"뜻": "경제학","변형": {"ivl'biekleitabus": "경제학적"}},
    "toatabus": {"뜻": "화학","변형": {"ivl'toatabus": "화학적"}},
    "cocfitabus": {"뜻": "논리학","변형": {"ivl'cocfitabus": "논리적"}},
    "lifitabus": {"뜻": "지리학","변형": {"ivl'lifitabus": "지리적"}},
    "suffitabus": {"뜻": "물리학","변형": {"ivl'suffitabus": "물리적"}},
    "jaiksuftabus": {"뜻": "생물학","변형": {"ivl'jaiksuftabus": "생물학적"}},
    "jisfitabus": {"뜻": "심리학","변형": {"ivl'jisfitabus": "심리적"}},
    "kifocus": {"뜻": "이론","변형": {"ivl'kifocus": "이론적"}},
    "baslekus": {"뜻": "감정","변형": {"ivl'baslekus": "감정적"}},
    "toacbiekus": {"뜻": "환경","변형": {"ivl'toacbiekus": "환경적"}},
    "kwijibus": {"뜻": "의식","변형": {"ivl'kwijibus": "의식적"}},
    "jaiksufus": {"뜻": "생물","변형": {"ivl'jaiksufus": "생물적"}},
    "jeibieius": {"뜻": "세계","변형": {"ivl'jeibieius": "세계적"}},
    "biefboaus": {"뜻": "결과","변형": {"ivl'biefboaus": "결과적"}},
    "qiekbiucus": {"뜻": "평균","변형": {"ivl'qiekbiucus": "평균적"}},
    "qiolucus": {"뜻": "표준","변형": {"ivl'qiolucus": "표준적"}},
    "baiciesus": {"뜻": "개념","변형": {"ivl'baiciesus": "개념적"}},
    "jaklikus": {"뜻": "상징","변형": {"ivl'jaklikus": "상징적"}},
    "siekkieius": {"뜻": "명예","변형": {"ivl'siekkieius": "명예적"}},
    "koigus": "외부",
    "caigus": "내부",
    "kafaius": "아래",
    "kuius": "위",
    "twisakus": "희망",
    "toalaklius": "화장지",
    "tiudaiqocus": "휴대폰",
    "toalakjifus": "화장실",
    "toajacus": "화산",
    "lejulius": "저수지",
    "tiekleius": "형제",
    "lasaius": "자매",
    "cassaius": "남매",
    "taikjekus": "행성",
    "taigiecus": "해변",
    "takbus": "항구",
    "tafkagelius": "할아버지",
    "tafsecius": "할머니",
    "takiacjaibus": "하얀색",
    "qius": "피",
    "qonwus": "포크",
    "judbafabus": "숟가락",
    "lejbafabus": "젓가락",
    "qieclius": "편지",
    "kiecqifus": "연필",
    "gofqeicus": "볼펜",
    "qifbibus": "필기구",
    "beijiqacus": "게시판",
    "qafacjaibus": "파란색",
    "peiffeigilecus": "텔레비전",
    "maibjakus": "책상",
    "pefus": "털",
    "paikiakus": "태양",
    "lacus": "잔",
    "nafus": "칼",
    "naqeius": "카페",
    "naseifaus": "카메라",
    "nadwus": "카드",
    "mijjofus": "칫솔",
    "mikiabus": "치약",
    "mijifus": "치실",
    "micbus": "친구",
    "mofobjaibus": "초록색",
    "maibus": "책",
    "maksucus": "창문",
    "kiufius": "유리",
    "ligus": "집",
    "licfous": "진로",
    "libus": "지구",
    "jujekus": "수성",
    "bwsjekus": "금성",
    "toajekus": "화성",
    "sobjekus": "목성",
    "pojekus": "토성",
    "meckoakjekus": "천왕성",
    "taikoakjekus": "해왕성",
    "siekkoakjekus": "명왕성",
    "libagus": "지갑",
    "lutoakjaibus": "주황색",
    "lokkius": "종이",
    "logusous": "조부모",
    "gusous": "부모",
    "legjius": "접시",
    "lesjisus": "점심",
    "kuecjus": "원수",
    "leciebus": "저녁",
    "jioqikus": "쇼핑",
    "lakius": "자유",
    "kikujus": "이웃",
    "kigufus": "이불",
    "daskious": "담요",
    "kifwsus": "이름",
    "kiggafus": "이빨",
    "kwilaus": "의자",
    "kwijaus": "의사",
    "kwskabus": "음악",
    "cofaius": "노래",
    "kwsjibus": "음식",
    "kuimius": "위치",
    "kuclecjaus": "운전사",
    "kiobjifus": "욕실",
    "kiofius": "요리",
    "koakus": "왕",
    "daipokfiekus": "대통령",
    "kofius": "오리",
    "kocwfus": "오늘",
    "keleius": "어제",
    "caikifus": "내일",
    "kieijufjaus": "예술사",
    "bwblakus": "극장",
    "kiektoaus": "영화",
    "kiekjakus": "영상",
    "kiefjoius": "열쇠",
    "lasufjoius": "자물쇠",
    "kiefus": "열",
    "kieckicus": "연인",
    "kiecbius": "연기",
    "kiebus": "역",
    "kiefwsus": "여름",
    "keicelius": "에너지",
    "keckeus": "언어",
    "kesecius": "어머니",
    "kiakus": "양",
    "kamisus": "아침",
    "kakius": "아이",
    "kagelius": "아버지",
    "kabius": "아기",
    "jeisiecdaius": "세면대",
    "siecus": "면",
    "jibsufus": "식물",
    "kiamaius": "야채",
    "jilakus": "시장",
    "jibdakus": "식당",
    "jilabus": "시작",
    "bbwpus": "끝",
    "jibofus": "시골",
    "gepwcus": "버튼",
    "juqus": "숲",
    "jubecus": "수건",
    "jocus": "손",
    "gafus": "발",
    "joliqusus": "소지품",
    "jogakboacus": "소방관",
    "jofius": "소리",
    "jous": "소",
    "judous": "수도",
    "jaibus": "색",
    "jaius": "새",
    "jatoius": "사회",
    "tobasus": "호감",
    "jabecus": "사건",
    "ggafbacjaibus": "빨간색",
    "gicus": "비누",
    "gius": "비",
    "gosus": "봄",
    "gofajaibus": "보라색",
    "giekkuecus": "병원",
    "giefus": "별",
    "mecdukus": "천둥",
    "gaisus": "뱀",
    "gaikus": "배우",
    "gasus": "밤",
    "gabsufboacus": "박물관",
    "gafasus": "바람",
    "gadabus": "바닥",
    "sucus": "문",
    "sulibaius": "무지개",
    "sofaius": "모래",
    "sodusus": "모둠",
    "saikifus": "매일",
    "sajus": "맛",
    "sakwfus": "마을",
    "dwkgufus": "등불",
    "doailius": "돼지",
    "dofus": "돌",
    "docus": "돈",
    "dojius": "도시",
    "bubbaus": "국가",
    "dojeboacus": "도서관",
    "dosagaisus": "도마뱀",
    "dofous": "도로",
    "dafbus": "닭",
    "dafus": "달",
    "dacmeius": "단체",
    "coius": "뇌",
    "coklakus": "농장",
    "cofacjaibus": "노란색",
    "casjaibus": "남색",
    "cafjjius": "날씨",
    "bbusus": "꿈",
    "bbomus": "꽃",
    "bbeglifus": "껍질",
    "bikebus": "기억",
    "bifwsus": "기름",
    "bufwsus": "구름",
    "boaklakus": "광장",
    "bokkuecus": "공원",
    "bokbius": "공기",
    "botiakus": "고향",
    "bokiakkius": "고양이",
    "bobius": "고기",
    "bieilefus": "계절",
    "biekmafus": "경찰",
    "biekufus": "겨울",
    "beskwcjaibus": "검은색",
    "baius": "개",
    "bacjibus": "간식",
    "bamubus": "가축",
    "balekus": "가정",
    "bakwfus": "가을",
    "bagakus": "가방",
    "babus": "가구",
    "cuckicus": "눈(동물의)",
    "cucmecus": "눈(내리는)",
    "dafikicus": "다리(동물의)",
    "dafimecus": "다리(건너는)"
  },
  "기본부사": {
    "cot": "부정",
    "bucmet": "가까이",
    "gefit": "매우",
    "seft": "멀리",
    "frtrt": "부분적으로",
    "kalibt": "아직",
    "fokt": "오래",
    "koacmect": "완전히",
    "kisit": "이미",
    "kilect": "이전",
    "kitut": "이후",
    "lectiet": "절대 / 전혀"
  },
  "동사": {
    "설정": {
      "1": "동사의 과거형은 동사에 'd'를 붙인다.",
      "2": "동사의 미래형은 동사에 'f'를 붙인다.",
      "3": "동사의 기본형은 모음으로 끝난다. 동사의 과거형을 'd'로 끝난다. 동사의 미래형은 'f'로 끝난다."
    },
    "bajna": {
      "뜻": "가다",
      "bajna": {
        "abajn": "산책/조깅",
        "elbajn": "걷는 자",
        "mubajn": "산책로/공원",
        "yl'bajna": "걷게/이동하게",
        "vl'bajna": "걸은"
      }
    },
    "genmi": {
      "뜻": "가르치다",
      "genmi": {
        "agenm": "교육",
        "elgenm": "선생님",
        "mugenm": {
          "뜻": "학교",
          "mugenm": {
            "mugenmvtk": "초등학교",
            "mugenmgrnk": "중학교",
            "mugenmhrnk": "고등학교",
            "mugenmcrnf": "대학교",
            "mugenmcmnk": "학원"
          }
        },
        "egenm": "학생",
        "thgenm": "교과서",
        "yl'genmi": "가르치게",
        "vl'genmi": "가르친"
      }
    },
    "dabtu": {
      "뜻": "대기하다",
      "dabtu": {
        "adabt": "대기/기다림",
        "eldabt": "대기자",
        "mudabt": "대기실/정류장",
        "yl'dabtu": "대기하게",
        "vl'dabtu": "대기한"
      }
    },
    "jamne": {
      "뜻": "사육하다",
      "jamne": {
        "ajamn": "사육",
        "eljamn": "사육자",
        "ejamn": "사육 당하는 것",
        "thjamn": "사육 도구",
        "mujamn": "사육장",
        "yl'jamne": "사육하게",
        "vl'jamne": "사육한"
      }
    },
    "jufno": {
      "뜻": "수리하다",
      "jufno": {
        "ajufn": "수리",
        "eljufn": "수리자",
        "thjufn": "수리 도구",
        "mujufn": "서비스 센터",
        "yl'jufno": "수리하게",
        "vl'jufno": "수리한"
      }
    },
    "cajna": {
      "뜻": "날다",
      "cajna": {
        "acajn": "비행/항공",
        "elcajn": "비행기 조종자(=파일럿)",
        "thcajn": "비행기",
        "mucajn": "활주로/공항",
        "yl'cajna": "비행하게",
        "vl'cajna": "비행한"
      }
    },
    "cojti": {
      "뜻": "여가를 즐기다",
      "cojti": {
        "acojt": "놀이",
        "elcojt": "놀이꾼",
        "thcojt": "장난감",
        "mucojt": "놀이터/놀이공원",
        "yl'cojti": "놀게",
        "vl'cojti": "여가를 즐긴"
      }
    },
    "cufmu": {
      "뜻": "가압하다",
      "cufmu": {
        "acufm": "가압/압박",
        "thcufm": "압축기/펌프",
        "mucufm": "압력실",
        "yl'cufmu": "압박하게",
        "vl'cufmu": "압박한"
      }
    },
    "dadke": {
      "뜻": "폐쇄하다",
      "dadke": {
        "adadk": "폐쇄",
        "thdadk": "자물쇠",
        "mudadk": "폐쇄 구역",
        "yl'dadke": "폐쇄하게",
        "vl'dadke": "폐쇄한"
      }
    },
    "mjino": {
      "뜻": "질주하다(달리다)",
      "mjino": {
        "amjin": "질주/레이싱",
        "elmjin": "주자/레이서",
        "thmjin": "경주차",
        "mumjin": "트랙/경기장",
        "yl'mjino": "질주하게",
        "vl'mjino": "질주한"
      }
    },
    "pumba": {
      "뜻": "투척하다",
      "pumba": {
        "apumb": "투척/발사",
        "elpumb": "투수/발사자",
        "thpumb": "투사체/공",
        "yl'pumba": "던지게",
        "vl'pumba": "던진"
      }
    },
    "gosni": {
      "뜻": "보살피다",
      "gosni": {
        "agosn": "보살핌/복지",
        "elgosn": "보호자",
        "egosn": "피보호자",
        "mugosn": "보호소",
        "yl'gosni": "보호하게",
        "vl'gosni": "보호한"
      }
    },
    "doglu": {
      "뜻": "돕다",
      "doglu": {
        "adogl": "조력/즈원",
        "eldogl": "조력자",
        "thdogl": "보조기구",
        "yl'doglu": "도와주게",
        "vl'doglu": "도와준"
      }
    },
    "mulbe": {
      "뜻": "추종/추적하다",
      "mulbe": {
        "amulb": "추적/추종",
        "elmulb": "추적자/팬",
        "thmulb": "추적기",
        "yl'mulbe": "따라가게",
        "vl'mulbe": "따라간"
      }
    },
    "sanko": {
      "뜻": "모방하다",
      "sanko": {
        "asank": "모방/모조",
        "elsank": "모방자",
        "thsank": "모조품",
        "yl'sanko": "모방하게",
        "vl'sanko": "모방한"
      }
    },
    "luvga": {
      "뜻": "주입하다",
      "luvga": {
        "aluvg": "주입/삽입",
        "elluvg": "주입기(사람)",
        "thluvg": "주사기/깔때기",
        "yl'luvga": "주입하게",
        "vl'luvga": "주입한"
      }
    },
    "patni": {
      "뜻": "낙하하다",
      "patni": {
        "apatn": "낙하/추락",
        "elpatn": "낙하자",
        "thpatn": "낙하산",
        "mupatn": "낙하지점",
        "yl'patni": "떨어지게",
        "vl'patni": "떨어진"
      }
    },
    "lesqu": {
      "뜻": "도약하다",
      "lesqu": {
        "alesq": "도약/점프",
        "ellesq": "도약자",
        "thlesq": "트램펄린",
        "yl'lesqu": "뛰게",
        "vl'lesqu": "뛴"
      }
    },
    "sjise": {
      "뜻": "마시다",
      "sjise": {
        "asjis": "음용",
        "elsjis": "음용자",
        "thsjis": "컵/음료수",
        "musjis": "급수대",
        "yl'sjise": "마시게",
        "vl'sjise": "마신"
      }
    },
    "scaso": {
      "뜻": "대면하다",
      "scaso": {
        "ascas": "대면/미팅",
        "elscas": "참석자",
        "muscas": "회의실",
        "yl'scaso": "대면하게",
        "vl'scaso": "대면한"
      }
    },
    "sadsa": {
      "뜻": "제작하다",
      "sadsa": {
        "asads": "제작/제조",
        "elsads": "제작자/엔지니어",
        "thsads": "제품/작품",
        "musads": "공장/작업실",
        "yl'sadsa": "만들게",
        "vl'sadsa": "만든"
      }
    },
    "pejmi": {
      "뜻": "접촉하다",
      "pejmi": {
        "apejm": "접촉/연락",
        "thpejm": "센서/터치패드",
        "yl'pejmi": "접촉하게",
        "vl'pejmi": "접촉한"
      }
    },
    "sulnu": {
      "뜻": "섭취하다",
      "sulnu": {
        "asuln": "식사",
        "elsuln": "식객",
        "thsuln": "수저/식기",
        "musuln": "식당",
        "yl'sulnu": "먹게",
        "vl'sulnu": "먹은"
      }
    },
    "dneke": {
      "뜻": "수령하다",
      "dneke": {
        "adnek": "수령/수신",
        "eldnek": "수신자",
        "thdnek": "수신기/안테나",
        "yl'dneke": "받게",
        "vl'dneke": "받은"
      }
    },
    "glono": {
      "뜻": "시청/관찰하다",
      "glono": {
        "aglon": "시청/관찰",
        "elglon": "관람객/관찰자",
        "thglon": "망원경/모니터",
        "muglon": "관측소",
        "yl'glono": "보게",
        "vl'glono": "본"
      }
    },
    "qabla": {
      "뜻": "파괴하다",
      "qabla": {
        "aqabl": "파괴/철거",
        "elqabl": "파괴자",
        "thqabl": "무기/분쇄기",
        "muqabl": "폐기장",
        "muqablud": "유적",
        "yl'qabla": "부수게",
        "vl'qabla": "부순"
      }
    },
    "bigni": {
      "뜻": "기립하다(일어서다)",
      "bigni": {
        "abign": "기립",
        "thbign": "받침대/스탠드",
        "yl'bigni": "서게",
        "vl'bigni": "선"
      }
    },
    "jublu": {
      "뜻": "은폐하다",
      "jublu": {
        "ajubl": "은폐/잠행",
        "thjubl": "위장망",
        "mujubl": "은신처",
        "yl'jublu": "숨게",
        "vl'jublu": "숨은"
      }
    },
    "juine": {
      "뜻": "휴식하다",
      "juine": {
        "ajuin": "휴식",
        "mujuin": "휴게소/쉼터",
        "yl'juine": "쉬게",
        "vl'juine": "쉰"
      }
    },
    "jinso": {
      "뜻": "심다",
      "jinso": {
        "ajins": "식재/농경",
        "eljins": "농부/정원사",
        "thjins": "모종/삽",
        "mujins": "농장/화단",
        "yl'jinso": "심게",
        "vl'jinso": "심은"
      }
    },
    "jesna": {
      "뜻": "착석하다",
      "jesna": {
        "ajesn": "착석",
        "thjesn": "의자/좌석",
        "yl'jesna": "앉게",
        "vl'jesna": "앉은"
      }
    },
    "oquci": {
      "뜻": "개방하다",
      "oqwci": {
        "aoquc": "개방",
        "thoquc": "열쇠/오프너",
        "yl'oquci": "열게",
        "vl'oquci": "연"
      }
    },
    "kingu": {
      "뜻": "착용하다",
      "kingu": {
        "aking": "착용",
        "thking": "옷/장비",
        "yl'kingu": "입게",
        "vl'kingu": "입은"
      }
    },
    "lanme": {
      "뜻": "취침하다",
      "lanme": {
        "alanm": "수면",
        "thlanm": "침구",
        "mulanm": "침실",
        "yl'lanme": "잠자게",
        "vl'lanme": "잔"
      }
    },
    "lafpo": {
      "뜻": "성장하다",
      "lafpo": {
        "alafp": "성장/발전",
        "thlafp": "비료",
        "yl'lafpo": "자라게",
        "vl'lafpo": "자란"
      }
    },
    "lanfa": {
      "뜻": "절단하다",
      "lanfa": {
        "alanf": "절단",
        "thlanf": "칼/가위",
        "yl'lanfa": "자르게",
        "vl'lanfa": "자른"
      }
    },
    "lajgi": {
      "뜻": "파지하다",
      "lajgi": {
        "alajg": "파지",
        "thlajg": "손잡이/집게",
        "yl'lajgi": "잡게",
        "vl'lajgi": "잡은"
      }
    },
    "lunnu": {
      "뜻": "제공하다",
      "lunnu": {
        "alunn": "제공/기부",
        "ellunn": "기부자",
        "elunn": "수혜자",
        "thlunn": "보급품/선물",
        "yl'lunnu": "주게",
        "vl'lunnu": "준"
      }
    },
    "lugle": {
      "뜻": "사망하다",
      "lugle": {
        "alugl": "사망",
        "mulugl": "무덤",
        "yl'lugle": "죽게",
        "vl'lugle": "죽은"
      }
    },
    "jaflo": {
      "뜻": "생존하다",
      "jaflo": {
        "ajafl": "생존/삶",
        "eljafl": "생존자",
        "thjafl": "생존도구",
        "eljafluf": "후손",
        "eljaflud": "조상",
        "yl'jaflo": "살게",
        "vl'jaflo": "산"
      }
    },
    "tniba": {
      "뜻": "포획하다",
      "tniba": {
        "atnib": "포획",
        "eltnib": "사냥꾼",
        "etnib": "사냥감",
        "thtnib": "그물/덫",
        "mutnib": "사냥터",
        "yl'tniba": "사냥하게",
        "vl'tniba": "사냥한"
      }
    },
    "safki": {
      "뜻": "말하다",
      "safki": {
        "asafk": "언어/말하기",
        "elsafk": "화자",
        "thsafk": "마이크",
        "yl'safki": "말하게",
        "vl'safki": "말한"
      }
    },
    "fuidu": {
      "뜻": "읽다",
      "fuidu": {
        "afuid": "독해",
        "elfuid": "독자",
        "yl'fuidu": "읽게",
        "vl'fuidu": "읽은"
      }
    },
    "labje": {
      "뜻": "작성하다",
      "labje": {
        "alabj": "작성/아기",
        "ellabj": "작성자",
        "yl'labje": "작성하게",
        "vl'labje": "작성한"
      }
    },
    "dundo": {
      "뜻": "듣다",
      "dundo": {
        "adund": "청취",
        "eldund": "청취자",
        "thdund": "이어폰",
        "yl'dundo": "듣게",
        "vl'dundo": "들은"
      }
    },
    "jiaka": {
      "뜻": "소리 지르다",
      "jiaka": {
        "ajiak": "고성/외침",
        "eljiak": "소리치는 자",
        "yl'jiaka": "소리치게",
        "vl'jiaka": "소리친"
      }
    },
    "jojbi": {
      "뜻": "속삭이다",
      "jojbi": {
        "ajojb": "속삭임",
        "eljojb": "속삭이는 자",
        "yl'jojbi": "속삭이게",
        "vl'jojbi": "속삭인"
      }
    },
    "jopku": {
      "뜻": "의사소통하다",
      "jopku": {
        "ajopk": "대화/소통",
        "eljopk": "대화 상대",
        "yl'jopku": "대화하게",
        "vl'jopku": "대화한"
      }
    },
    "lisce": {
      "뜻": "질문하다",
      "lisce": {
        "alisc": "질문/질의",
        "ellisc": "질문자",
        "elisc": "답변자",
        "yl'lisce": "질문하게",
        "vl'lisce": "질문한"
      }
    },
    "lefno": {
      "뜻": "자리하다(위치하다)",
      "lefno": {
        "alefn": "자리/위치",
        "yl'lefno": "자리하게/위치하게",
        "vl'lefno": "자리한/위치한"
      }
    },
    "ulfla": {
      "뜻": "울다",
      "ulfla": {
        "aulfl": "눈물",
        "vl'ulfla": "운(과거에 울었던)",
        "yl'ulfla": "울게"
      }
    },
    "uljti": {
      "뜻": "웃다",
      "uljti": {
        "auljt": "웃음",
        "yl'uljti": "웃게",
        "vl'uljti": "웃은"
      }
    },
    "flecu": {
      "뜻": "발전하다",
      "flecu": {
        "aflec": "발전/발달",
        "yl'flecu": "발전하게",
        "vl'flecu": "발전한"
      }
    },
    "sujqe": {
      "뜻": "무시하다",
      "sujqe": {
        "asujq": "무시",
        "vl'sujqe": "무시한",
        "yl'sujqe": "무시하게"
      }
    },
    "qobpo": {
      "뜻": "포기하다",
      "qobpo": {
        "aqobp": "포기",
        "vl'qobpo": "포기한",
        "yl'qobpo": "포기하게"
      }
    },
    "qinta": {
      "뜻": "피하다",
      "qinta": {
        "aqint": "회피",
        "vl'qinta": "피한",
        "yl'qinta": "피하게"
      }
    },
    "lanki": {
      "뜻": "주장하다",
      "lanki": {
        "alank": "주장",
        "vl'lanki": "주장한",
        "yl'lanki": "주장하게"
      }
    },
    "balfu": {
      "뜻": "거절하다",
      "balfu": {
        "abalf": "거절",
        "vl'balfu": "거절한",
        "yl'balfu": "거절하게"
      }
    },
    "prane": {
      "뜻": "빠르다",
      "변형": {
        "yl'prane": "빠르게",
        "vl'prane": "빠른"
      }
    },
    "crano": {
      "뜻": "느리다",
      "변형": {
        "yl'crano": "느리게",
        "vl'crano": "느린"
      }
    },
    "medna": {
      "뜻": "필요하다",
      "변형": {
        "yl'medna": "필요하게",
        "vl'medna": "필요한"
      }
    },
    "mtkni": {
      "뜻": "피곤하다",
      "변형": {
        "yl'mtkni": "피곤하게",
        "vl'mtkni": "피곤한"
      }
    },
    "vtknu": {
      "뜻": "힘들다",
      "변형": {
        "yl'vtknu": "힘들게",
        "vl'vtknu": "힘든"
      }
    },
    "crnfe": {
      "뜻": "크다",
      "변형": {
        "yl'crnfe": "크게",
        "vl'crnfe": "큰"
      }
    },
    "vknto": {
      "뜻": "작다",
      "변형": {
        "yl'vknto": "작게",
        "vl'vknto": "작은"
      }
    },
    "trnna": {
      "뜻": "없다",
      "변형": {
        "yl'trnna": "없게",
        "vl'trnna": "없는"
      }
    },
    "lenli": {
      "뜻": "있다",
      "변형": {
        "yl'lenli": "있게",
        "vl'lenli": "있는"
      }
    },
    "hrknu": {
      "뜻": "높다",
      "변형": {
        "yl'hrknu": "높게",
        "vl'hrknu": "높은"
      }
    },
    "grkne": {
      "뜻": "낮다",
      "변형": {
        "yl'grkne": "낮게",
        "vl'grkne": "낮은"
      }
    },
    "ballo": {
      "뜻": "가정하다",
      "ballo": {
        "aball": "가정",
        "vl'ballo": "가정한",
        "yl'ballo": "가정하게"
      }
    },
    "qagla": {
      "뜻": "패배하다",
      "qagla": {
        "aqagl": "패배",
        "vl'qagla": "패배한",
        "yl'qagla": "패배하게",
        "elqagl": "패배자"
      }
    },
    "gacki": {
      "뜻": "반응하다",
      "gacki": {
        "yl'agaci": "반응",
        "vl'gacki": "반응한",
        "gackj": "반응하게"
      }
    },
    "mulnu": {
      "뜻": "출판하다",
      "mulnu": {
        "amuln": "출판",
        "vl'mulnu": "출판한",
        "yl'mulnu": "출판하게"
      }
    },
    "kjibe": {
      "뜻": "장식하다",
      "kjibe": {
        "akjib": "장식",
        "vl'kjibe": "장식한",
        "yl'kjibe": "장식하게"
      }
    },
    "ktato": {
      "뜻": "방해하다",
      "ktato": {
        "aktat": "방해",
        "vl'ktato": "방해한",
        "yl'ktato": "방해하게"
      }
    },
    "jlaka": {
      "뜻": "보상하다",
      "jlaka": {
        "ajlak": "보상",
        "vl'jlaka": "보상한",
        "yl'jlaka": "보상하게"
      }
    },
    "sgabu": {
      "뜻": "명백하다",
      "sgabu": {
        "asgab": "명백",
        "vl'sgabu": "명백한",
        "yl'sgabu": "명백하게"
      }
    },
    "tejne": {
      "뜻": "협상하다",
      "tejne": {
        "atejn": "협상",
        "vl'tejne": "협상한",
        "yl'tejne": "협상하게"
      }
    },
    "tuoto": {
      "뜻": "후회하다",
      "tuoto": {
        "atuot": "후회",
        "vl'tuoto": "후회한",
        "yl'tuoto": "후회하게"
      }
    },
    "toaba": {
      "뜻": "정확하다",
      "toaba": {
        "atoab": "정확",
        "vl'toaba": "정확한",
        "yl'toaba": "정확하게"
      }
    },
    "dleci": {
      "뜻": "도전하다",
      "dleci": {
        "adlec": "도전",
        "vl'dleci": "도전한",
        "yl'dleci": "도전하게",
        "eldlec": "도전자"
      }
    },
    "klinu": {
      "뜻": "중지하다",
      "klinu": {
        "aklin": "중지",
        "vl'klinu": "중지한",
        "yl'klinu": "중지하게"
      }
    },
    "fiebe": {
      "뜻": "협력하다",
      "fiebe": {
        "afieb": "협력",
        "vl'fiebe": "협력한",
        "yl'fiebe": "협력하게",
        "elfieb": "협력자"
      }
    },
    "tlago": {
      "뜻": "적합하다",
      "tlago": {
        "atlag": "적합",
        "vl'tlago": "적합한",
        "yl'tlago": "적합하게",
        "eltlag": "적합자"
      }
    },
    "jajna": {
      "뜻": "상속하다",
      "jajna": {
        "ajajn": "상속",
        "vl'jajna": "상속한",
        "yl'jajna": "상속하게"
      }
    },
    "fieci": {
      "뜻": "실현하다",
      "fieci": {
        "afiec": "실현",
        "vl'fieci": "실현한",
        "yl'fieci": "실현하게"
      }
    },
    "kenfu": {
      "뜻": "동일하다",
      "kenfu": {
        "akenf": "동일",
        "vl'kenfu": "동일한",
        "yl'kenfu": "동일하게"
      }
    },
    "ladke": {
      "뜻": "작동하다",
      "ladke": {
        "aladk": "작동",
        "vl'ladke": "작동한",
        "yl'ladke": "작동하게"
      }
    },
    "sijlo": {
      "뜻": "묘사하다",
      "sijlo": {
        "asijl": "묘사",
        "vl'sijlo": "묘사한",
        "yl'sijlo": "묘사하게"
      }
    },
    "jeufa": {
      "뜻": "서술하다",
      "jeufa": {
        "ajeuf": "서술",
        "vl'jeufa": "서술한",
        "yl'jeufa": "서술하게"
      }
    },
    "cakni": {
      "뜻": "안내하다",
      "cakni": {
        "acakn": "안내",
        "vl'cakni": "안내한",
        "yl'cakni": "안내하게"
      }
    },
    "tunku": {
      "뜻": "훌륭하다",
      "tunku": {
        "atunk": "훌륭",
        "vl'tunku": "훌륭한",
        "yl'tunku": "훌륭하게"
      }
    },
    "daice": {
      "뜻": "대단하다",
      "daice": {
        "adaic": "대단",
        "vl'daice": "대단한",
        "yl'daice": "대단하게"
      }
    },
    "bulpo": {
      "뜻": "구조하다",
      "bulpo": {
        "abulp": "구조",
        "vl'bulpo": "구조한",
        "yl'bulpo": "구조하게"
      }
    },
    "baifa": {
      "뜻": "폭발하다",
      "baifa": {
        "abaif": "폭발",
        "vl'baifa": "폭발한",
        "yl'baifa": "폭발하게"
      }
    },
    "mesli": {
      "뜻": "첨부하다",
      "mesli": {
        "amesl": "첨부",
        "vl'mesli": "첨부한",
        "yl'mesli": "첨부하게"
      }
    },
    "mosnu": {
      "뜻": "총명하다",
      "mosnu": {
        "amosn": "총명",
        "vl'mosnu": "총명한",
        "yl'mosnu": "총명하게"
      }
    },
    "cijne": {
      "뜻": "완수하다",
      "cijne": {
        "acijn": "완수",
        "vl'cijne": "완수한",
        "yl'cijne": "완수하게"
      }
    },
    "kenno": {
      "뜻": "유일하다",
      "kenno": {
        "akenn": "유일",
        "vl'kenno": "유일한",
        "yl'kenno": "유일하게"
      }
    },
    "kfoba": {
      "뜻": "등록하다",
      "kfoba": {
        "akfob": "등록",
        "vl'kfoba": "등록한",
        "yl'kfoba": "등록하게"
      }
    },
    "kutgi": {
      "뜻": "위협하다",
      "kutgi": {
        "akutg": "위협",
        "vl'kutgi": "위협한",
        "yl'kutgi": "위협하게"
      }
    },
    "jumgu": {
      "뜻": "성취하다",
      "jumgu": {
        "ajumg": "성취",
        "vl'jumgu": "성취한",
        "yl'jumgu": "성취하게"
      }
    },
    "giqce": {
      "뜻": "비판하다",
      "giqce": {
        "agiqc": "비판",
        "vl'giqce": "비판한",
        "yl'giqce": "비판하게"
      }
    },
    "bjaco": {
      "뜻": "확산하다",
      "bjaco": {
        "abjac": "확산",
        "vl'bjaco": "확산한",
        "yl'bjaco": "확산하게"
      }
    },
    "qekga": {
      "뜻": "평범하다",
      "qekga": {
        "aqekg": "평범",
        "vl'qekga": "평범한",
        "yl'qekga": "평범하게"
      }
    },
    "ketki": {
      "뜻": "여행하다",
      "ketki": {
        "aketk": "여행",
        "vl'ketki": "여행한",
        "yl'ketki": "여행하게",
        "elketk": "여행자"
      }
    },
    "gelku": {
      "뜻": "집중하다",
      "gelku": {
        "agelk": "집중",
        "vl'gelku": "집중한",
        "yl'gelku": "집중하게"
      }
    },
    "jtace": {
      "뜻": "순환하다",
      "jtace": {
        "ajtac": "순환",
        "vl'jtace": "순환한",
        "yl'jtace": "순환하게"
      }
    },
    "jaiko": {
      "뜻": "희생하다",
      "jaiko": {
        "ajaik": "희생",
        "vl'jaiko": "희생한",
        "yl'jaiko": "희생하게"
      }
    },
    "stesa": {
      "뜻": "탐험하다",
      "stesa": {
        "astes": "탐험",
        "vl'stesa": "탐험한",
        "yl'stesa": "탐험하게"
      }
    },
    "kiabi": {
      "뜻": "예약하다",
      "kiabi": {
        "akiab": "예약",
        "vl'kiabi": "예약한",
        "yl'kiabi": "예약하게"
      }
    },
    "mejcu": {
      "뜻": "추천하다",
      "mejcu": {
        "amejc": "추천",
        "vl'mejcu": "추천한",
        "yl'mejcu": "추천하게"
      }
    },
    "glace": {
      "뜻": "비난하다",
      "glace": {
        "aglac": "비난",
        "vl'glace": "비난한",
        "yl'glace": "비난하게"
      }
    },
    "cjifo": {
      "뜻": "손실하다",
      "cjifo": {
        "acjif": "손실",
        "vl'cjifo": "손실한",
        "yl'cjifo": "손실하게"
      }
    },
    "jefba": {
      "뜻": "설득하다",
      "jefba": {
        "ajefb": "설득",
        "vl'jefba": "설득한",
        "yl'jefba": "설득하게"
      }
    },
    "bladi": {
      "뜻": "거대하다",
      "bladi": {
        "ablad": "거대",
        "vl'bladi": "거대한",
        "yl'bladi": "거대하게"
      }
    },
    "klaku": {
      "뜻": "경쟁하다",
      "klaku": {
        "aklak": "경쟁",
        "vl'klaku": "경쟁한",
        "yl'klaku": "경쟁하게"
      }
    },
    "tjake": {
      "뜻": "회상하다",
      "tjake": {
        "atjak": "회상",
        "vl'tjake": "회상한",
        "yl'tjake": "회상하게"
      }
    },
    "menlo": {
      "뜻": "추최하다",
      "menlo": {
        "amenl": "추최",
        "vl'menlo": "추최한",
        "yl'menlo": "추최하게"
      }
    },
    "ginba": {
      "뜻": "비교하다",
      "ginba": {
        "aginb": "비교",
        "vl'ginba": "비교한",
        "yl'ginba": "비교하게"
      }
    },
    "bujki": {
      "뜻": "구성하다",
      "bujki": {
        "abujk": "구성",
        "vl'bujki": "구성한",
        "yl'bujki": "구성하게"
      }
    },
    "wsliu": {
      "뜻": "금지하다",
      "wsliu": {
        "awsli": "금지",
        "vl'wsliu": "금지한",
        "yl'wsliu": "금지하게"
      }
    },
    "bifbe": {
      "뜻": "기록하다",
      "bifbe": {
        "abifb": "기록",
        "vl'bifbe": "기록한",
        "yl'bifbe": "기록하게"
      }
    },
    "qekbo": {
      "뜻": "평가하다",
      "qekbo": {
        "aqekb": "평가",
        "vl'qekbo": "평가한",
        "yl'qekbo": "평가하게"
      }
    },
    "kieca": {
      "뜻": "유연하다",
      "kieca": {
        "akiec": "유연",
        "vl'kieca": "유연한",
        "yl'kieca": "유연하게"
      }
    },
    "lunki": {
      "뜻": "중요하다",
      "lunki": {
        "alunk": "중요",
        "vl'lunki": "중요한",
        "yl'lunki": "중요하게"
      }
    },
    "bafku": {
      "뜻": "갈등하다",
      "bafku": {
        "abafk": "갈등",
        "vl'bafku": "갈등한",
        "yl'bafku": "갈등하게"
      }
    },
    "biefe": {
      "뜻": "격리하다",
      "biefe": {
        "abief": "격리",
        "vl'biefe": "격리한",
        "yl'biefe": "격리하게"
      }
    },
    "bleko": {
      "뜻": "교정하다",
      "bleko": {
        "ablek": "교정",
        "vl'bleko": "교정한",
        "yl'bleko": "교정하게"
      }
    },
    "legca": {
      "뜻": "접근하다",
      "legca": {
        "alegc": "접근",
        "vl'legca": "접근한",
        "yl'legca": "접근하게"
      }
    },
    "jefmi": {
      "뜻": "설치하다",
      "jefmi": {
        "ajefm": "설치",
        "vl'jefmi": "설치한",
        "yl'jefmi": "설치하게"
      }
    },
    "kuifu": {
      "뜻": "위로하다",
      "kuifu": {
        "akuif": "위로",
        "vl'kuifu": "위로한",
        "yl'kuifu": "위로하게"
      }
    },
    "gidfe": {
      "뜻": "배달하다",
      "gidfe": {
        "agidf": "배달",
        "vl'gidfe": "배달한",
        "yl'gidfe": "배달하게"
      }
    },
    "blefo": {
      "뜻": "적절하다",
      "blefo": {
        "ablef": "적절",
        "vl'blefo": "적절한",
        "yl'blefo": "적절하게"
      }
    },
    "benka": {
      "뜻": "기증하다",
      "benka": {
        "abenk": "기증",
        "vl'benka": "기증한",
        "yl'benka": "기증하게"
      }
    },
    "jonbu": {
      "뜻": "성숙하다",
      "jonbu": {
        "ajonb": "성숙",
        "vl'jonbu": "성숙한",
        "yl'jonbu": "성숙하게"
      }
    },
    "sulte": {
      "뜻": "출발하다",
      "sulte": {
        "asult": "출발",
        "vl'sulte": "출발한",
        "yl'sulte": "출발하게"
      }
    },
    "jufbo": {
      "뜻": "수락하다",
      "jufbo": {
        "ajufb": "수락",
        "vl'jufbo": "수락한",
        "yl'jufbo": "수락하게"
      }
    },
    "kjisa": {
      "뜻": "극심하다",
      "kjisa": {
        "akjis": "극심",
        "vl'kjisa": "극심한",
        "yl'kjisa": "극심하게"
      }
    },
    "kjaki": {
      "뜻": "이상하다",
      "kjaki": {
        "akjak": "이상",
        "vl'kjaki": "이상한",
        "yl'kjaki": "이상하게"
      }
    },
    "tabnu": {
      "뜻": "해결하다",
      "tabnu": {
        "atabn": "해결",
        "vl'tabnu": "해결한",
        "yl'tabnu": "해결하게"
      }
    },
    "javle": {
      "뜻": "사과하다",
      "javle": {
        "ajavl": "사과",
        "vl'javle": "사과한",
        "yl'javle": "사과하게"
      }
    },
    "gecto": {
      "뜻": "변화하다",
      "gecto": {
        "agect": "변화",
        "vl'gecto": "변화한",
        "yl'gecto": "변화하게"
      }
    },
    "jigta": {
      "뜻": "비슷하다",
      "jigta": {
        "ajigt": "비슷",
        "vl'jigta": "비슷한",
        "yl'jigta": "비슷하게"
      }
    },
    "cleci": {
      "뜻": "완전하다",
      "cleci": {
        "aclec": "완전",
        "vl'cleci": "완전한",
        "yl'cleci": "완전하게"
      }
    },
    "tejlu": {
      "뜻": "흡수하다",
      "tejlu": {
        "atejl": "흡수",
        "vl'tejlu": "흡수한",
        "yl'tejlu": "흡수하게"
      }
    },
    "pevte": {
      "뜻": "적응하다",
      "pevte": {
        "apevt": "적응",
        "vl'pecte": "적응한",
        "yl'pevte": "적응하게"
      }
    },
    "bolko": {
      "뜻": "존경하다",
      "bolko": {
        "abolk": "존경",
        "vl'bolko": "존경한",
        "yl'bolko": "존경하게"
      }
    },
    "kemba": {
      "뜻": "예측하다",
      "kemba": {
        "akemb": "예측",
        "vl'kemba": "예측한",
        "yl'kemba": "예측하게"
      }
    },
    "betni": {
      "뜻": "결합하다",
      "betni": {
        "abetn": "결합",
        "vl'betni": "결합한",
        "yl'betni": "결합하게"
      }
    },
    "gusku": {
      "뜻": "불평하다",
      "gusku": {
        "agusk": "불평",
        "vl'gusku": "불평한",
        "yl'gusku": "불평하게"
      }
    },
    "jumfe": {
      "뜻": "수출하다",
      "jumfe": {
        "ajumf": "수출",
        "vl'jumfe": "수출한",
        "yl'jumfe": "수출하게"
      }
    },
    "blako": {
      "뜻": "과장하다",
      "blako": {
        "ablak": "과장",
        "vl'blako": "과장한",
        "yl'blako": "과장하게"
      }
    },
    "donka": {
      "뜻": "동의하다",
      "donka": {
        "adonk": "동의",
        "vl'donka": "동의한",
        "yl'donka": "동의하게"
      }
    },
    "bifgi": {
      "뜻": "독립하다",
      "bifgi": {
        "abifg": "독립",
        "vl'bifgi": "독립한",
        "yl'bifgi": "독립하게"
      }
    },
    "sieku": {
      "뜻": "설명하다",
      "sieku": {
        "asiek": "설명",
        "vl'sieku": "설명한",
        "yl'sieku": "설명하게"
      }
    },
    "bajge": {
      "뜻": "간섭하다",
      "bajge": {
        "abajg": "간섭",
        "vl'bajge": "간섭한",
        "yl'bajge": "간섭하게"
      }
    },
    "bolno": {
      "뜻": "간과하다",
      "bolno": {
        "aboln": "간과",
        "vl'bolno": "간과한",
        "yl'bolno": "간과하게"
      }
    },
    "bolga": {
      "뜻": "고집하다",
      "bolga": {
        "abolg": "고집",
        "vl'bolga": "고집한",
        "yl'bolga": "고집하게"
      }
    },
    "kjaci": {
      "뜻": "생산하다",
      "kjaci": {
        "akjac": "생산",
        "vl'kjaci": "생산한",
        "yl'kjaci": "생산하게"
      }
    },
    "ctiku": {
      "뜻": "진행하다",
      "ctiku": {
        "actik": "진행",
        "vl'ctiku": "진행한",
        "yl'ctiku": "진행하게"
      }
    },
    "klece": {
      "뜻": "충전하다",
      "klece": {
        "aklec": "충전",
        "vl'klece": "충전한",
        "yl'klece": "충전하게"
      }
    },
    "bomlo": {
      "뜻": "교체하다",
      "bomlo": {
        "aboml": "교체",
        "vl'bomlo": "교체한",
        "yl'bomlo": "교체하게"
      }
    },
    "leiba": {
      "뜻": "제거하다",
      "leiba": {
        "aleib": "제거",
        "vl'leiba": "제거한",
        "yl'leiba": "제거하게"
      }
    },
    "daiqi": {
      "뜻": "대표하다",
      "daiqi": {
        "adaiq": "대표",
        "vl'daiqi": "대표한",
        "yl'daiqi": "대표하게"
      }
    },
    "guvfu": {
      "뜻": "분리하다",
      "guvfu": {
        "aguvf": "분리",
        "vl'guvfu": "분리한",
        "yl'guvfu": "분리하게"
      }
    },
    "siese": {
      "뜻": "미묘하다",
      "siese": {
        "asies": "미묘",
        "vl'siese": "미묘한",
        "yl'siese": "미묘하게"
      }
    },
    "zetho": {
      "뜻": "번역하다",
      "zetho": {
        "azeth": "번역",
        "vl'zetho": "번역한",
        "yl'zetho": "번역하게"
      }
    },
    "jueka": {
      "뜻": "수정하다",
      "jueka": {
        "ajuek": "수정",
        "vl'jueka": "수정한",
        "yl'jueka": "수정하게"
      }
    },
    "kiufi": {
      "뜻": "유래하다",
      "kiufi": {
        "akiuf": "유래",
        "vl'kiufi": "유래한",
        "yl'kiufi": "유래하게"
      }
    },
    "jinfu": {
      "뜻": "실패하다",
      "jinfu": {
        "ajinf": "실패",
        "vl'jinfu": "실패한",
        "yl'jinfu": "실패하게"
      }
    },
    "kurhe": {
      "뜻": "긴급하다",
      "kurhe": {
        "akurh": "긴급",
        "vl'kurhe": "긴급한",
        "yl'kurhe": "긴급하게"
      }
    },
    "casbo": {
      "뜻": "난폭하다",
      "casbo": {
        "acasb": "난폭",
        "vl'casbo": "난폭한",
        "yl'casbo": "난폭하게"
      }
    },
    "janka": {
      "뜻": "상상하다",
      "janka": {
        "ajank": "상상",
        "vl'janka": "상상한",
        "yl'janka": "상상하게",
        "thjank": "사진"
      }
    },
    "cleni": {
      "뜻": "인지하다/눈치채다",
      "cleni": {
        "aclen": "인지/눈치",
        "vl'cleni": "인지한/눈치챈",
        "yl'cleni": "인지하게/눈치채게",
        "doksaclen": "자아"
      }
    },
    "leiku": {
      "뜻": "제외하다",
      "leiku": {
        "aleik": "제외",
        "vl'leiku": "제외한",
        "yl'leiku": "제외하게"
      }
    },
    "tanse": {
      "뜻": "포함하다",
      "tanse": {
        "atans": "포함",
        "vl'tanse": "포함한",
        "yl'tanse": "포함하게"
      }
    },
    "lonlo": {
      "뜻": "고귀하다",
      "lonlo": {
        "alonl": "고귀",
        "vl'lonlo": "고귀한",
        "yl'lonlo": "고귀하게"
      }
    },
    "laita": {
      "뜻": "재현하다",
      "laita": {
        "alait": "재현",
        "vl'laita": "재현한",
        "yl'laita": "재현하게"
      }
    },
    "solgi": {
      "뜻": "모집하다",
      "solgi": {
        "asolg": "모집",
        "vl'solgi": "모집한",
        "yl'solgi": "모집하게"
      }
    },
    "melku": {
      "뜻": "채용하다",
      "melku": {
        "amelk": "채용",
        "vl'melku": "채용한",
        "yl'melku": "채용하게"
      }
    },
    "jeige": {
      "뜻": "설립하다",
      "jeige": {
        "ajeig": "설립",
        "vl'jeige": "설립한",
        "yl'jeige": "설립하게"
      }
    },
    "globo": {
      "뜻": "부족하다",
      "globo": {
        "aglob": "부족",
        "vl'globo": "부족한",
        "yl'globo": "부족하게"
      }
    },
    "kebna": {
      "뜻": "언급하다",
      "kebna": {
        "akebn": "언급",
        "vl'kebna": "언급한",
        "yl'kebna": "언급하게"
      }
    },
    "basji": {
      "뜻": "감시하다",
      "basji": {
        "abasj": "감시",
        "vl'basji": "감시한",
        "yl'basji": "감시하게"
      }
    },
    "cleku": {
      "뜻": "인정하다",
      "cleku": {
        "aclek": "인정",
        "vl'cleku": "인정한",
        "yl'cleku": "인정하게"
      }
    },
    "tefbe": {
      "뜻": "허락하다",
      "tefbe": {
        "atefb": "허락",
        "vl'tefbe": "허락한",
        "yl'tefbe": "허락하게"
      }
    },
    "gleko": {
      "뜻": "부정하다",
      "gleko": {
        "aglek": "부정",
        "vl'gleko": "부정한",
        "yl'gleko": "부정하게"
      }
    },
    "bleka": {
      "뜻": "특정하다",
      "bleka": {
        "ablek": "특정",
        "vl'bleka": "특정한",
        "yl'bleka": "특정하게"
      }
    },
    "giefi": {
      "뜻": "특별하다",
      "giefi": {
        "agief": "특별",
        "vl'giefi": "특별한",
        "yl'giefi": "특별하게"
      }
    },
    "cmeku": {
      "뜻": "간청하다",
      "cmeku": {
        "acmek": "간청",
        "vl'cmeku": "간청한",
        "yl'cmeku": "간청하게"
      }
    },
    "ktese": {
      "뜻": "경험하다",
      "ktese": {
        "aktes": "경험",
        "vl'ktese": "경험한",
        "yl'ktese": "경험하게"
      }
    },
    "henbo": {
      "뜻": "반복하다",
      "henbo": {
        "ahenb": "반복",
        "vl'henbo": "반복한",
        "yl'henbo": "반복하게"
      }
    },
    "klota": {
      "뜻": "강조하다",
      "klota": {
        "aklot": "강조",
        "vl'klota": "강조한",
        "yl'klota": "강조하게"
      }
    },
    "fieti": {
      "뜻": "화려하다",
      "fieti": {
        "afiet": "화려",
        "vl'fieti": "화려한",
        "yl'fieti": "화려하게"
      }
    },
    "jolku": {
      "뜻": "소중하다",
      "jolku": {
        "ajolk": "소중",
        "vl'jolku": "소중한",
        "yl'jolku": "소중하게"
      }
    },
    "pilke": {
      "뜻": "귀중하다",
      "pilke": {
        "apilk": "귀중",
        "vl'pilke": "귀중한",
        "yl'pilke": "귀중하게"
      }
    },
    "manco": {
      "뜻": "칭찬하다",
      "manco": {
        "amanc": "칭찬",
        "vl'manco": "칭찬한",
        "yl'manco": "칭찬하게"
      }
    },
    "garda": {
      "뜻": "반대하다",
      "garda": {
        "agard": "반대",
        "vl'garda": "반대한",
        "yl'garda": "반대하게",
        "elgard": "반대자"
      }
    },
    "letki": {
      "뜻": "저항하다",
      "letki": {
        "aletk": "저항",
        "vl'letki": "저항한",
        "yl'letki": "저항하게"
      }
    },
    "tjeku": {
      "뜻": "합성하다",
      "tjeku": {
        "atjek": "합성",
        "vl'tjeku": "합성한",
        "yl'tjeku": "합성하게"
      }
    },
    "lunke": {
      "뜻": "주요하다",
      "lunke": {
        "alunk": "주요",
        "vl'lunkv": "주요한",
        "yl'lunkj": "주요하게"
      }
    },
    "gluko": {
      "뜻": "입증하다",
      "gluko": {
        "agluk": "입증",
        "vl'gluko": "입증한",
        "yl'gluko": "입증하게"
      }
    },
    "cjeka": {
      "뜻": "찬성하다",
      "cjeka": {
        "acjek": "찬성",
        "vl'cjeka": "찬성한",
        "yl'cjeka": "찬성하게",
        "elcjek": "찬성자"
      }
    },
    "mubni": {
      "뜻": "추구하다",
      "mubni": {
        "amubn": "추구",
        "vl'mubni": "추구한",
        "yl'mubni": "추구하게"
      }
    },
    "bleku": {
      "뜻": "확정하다",
      "bleku": {
        "ablek": "확정",
        "vl'bleku": "확정한",
        "yl'bleku": "확정하게"
      }
    },
    "tafke": {
      "뜻": "할당하다",
      "tafke": {
        "atafk": "할당",
        "vl'tafke": "할당한",
        "yl'tafke": "할당하게"
      }
    },
    "dluko": {
      "뜻": "중대하다",
      "dluko": {
        "adluk": "중대",
        "vl'dluko": "중대한",
        "yl'dluko": "중대하게"
      }
    },
    "lanba": {
      "뜻": "자극하다",
      "lanba": {
        "alanb": "자극",
        "vl'lanba": "자극한",
        "yl'lanba": "자극하게"
      }
    },
    "fleki": {
      "뜻": "일정하다",
      "fleki": {
        "aflek": "일정",
        "vl'fleki": "일정한",
        "yl'fleki": "일정하게"
      }
    },
    "kuecu": {
      "뜻": "복원하다",
      "kuecu": {
        "akuec": "복원",
        "vl'kuecu": "복원한",
        "yl'kuecu": "복원하게"
      }
    },
    "bluce": {
      "뜻": "꾸준하다",
      "bluce": {
        "abluc": "꾸준",
        "vl'bluce": "꾸준한",
        "yl'bluce": "꾸준하게"
      }
    },
    "kirbo": {
      "뜻": "연구하다",
      "kirbo": {
        "akirb": "연구",
        "vl'kirbo": "연구한",
        "yl'kirbo": "연구하게",
        "mukirbo": "연구실"
      }
    },
    "kesba": {
      "뜻": "엄격하다",
      "kesba": {
        "akesb": "엄격",
        "vl'kesba": "엄격한",
        "yl'kesba": "엄격하게"
      }
    },
    "daimi": {
      "뜻": "대체하다",
      "daimi": {
        "adaim": "대체",
        "vl'daimi": "대체한",
        "yl'daimi": "대체하게"
      }
    },
    "joglu": {
      "뜻": "소비하다",
      "joglu": {
        "ajogl": "소비",
        "vl'joglu": "소비한",
        "yl'joglu": "소비하게"
      }
    },
    "fiefe": {
      "뜻": "강렬하다",
      "fiefe": {
        "afief": "강렬",
        "vl'fiefe": "강렬한",
        "yl'fiefe": "강렬하게"
      }
    },
    "fjeko": {
      "뜻": "달성하다",
      "fjeko": {
        "afjek": "달성",
        "vl'fjeko": "달성한",
        "yl'fjeko": "달성하게"
      }
    },
    "toiba": {
      "뜻": "획득하다",
      "toiba": {
        "atoib": "획득",
        "vl'toiba": "획득한",
        "yl'toiba": "획득하게"
      }
    },
    "glaki": {
      "뜻": "예방하다",
      "glaki": {
        "aglak": "예방",
        "vl'glaki": "예방한",
        "yl'glaki": "예방하게"
      }
    },
    "cfinu": {
      "뜻": "편리하다",
      "cfinu": {
        "acfin": "편리",
        "vl'cfinu": "편리한",
        "yl'cfinu": "편리하게"
      }
    },
    "ciese": {
      "뜻": "기념하다",
      "ciese": {
        "acies": "기념",
        "vl'ciese": "기념한",
        "yl'ciese": "기념하게"
      }
    },
    "csiko": {
      "뜻": "선명하다",
      "csiko": {
        "acsik": "선명",
        "vl'csiko": "선명한",
        "yl'csiko": "선명하게"
      }
    },
    "kjaka": {
      "뜻": "생생하다",
      "kjaka": {
        "akjak": "생생",
        "vl'kjaka": "생생한",
        "yl'kjaka": "생생하게"
      }
    },
    "penbi": {
      "뜻": "경고하다",
      "penbi": {
        "apenb": "경고",
        "vl'penbi": "경고한",
        "yl'penbi": "경고하게"
      }
    },
    "fsaku": {
      "뜻": "실망하다",
      "fsaku": {
        "afsak": "실망",
        "vl'fsaku": "실망한",
        "yl'fsaku": "실망하게"
      }
    },
    "cjise": {
      "뜻": "무관심하다",
      "cjise": {
        "acjis": "무관심",
        "vl'cjise": "무관심한",
        "yl'cjise": "무관심하게"
      }
    },
    "dakto": {
      "뜻": "당황하다",
      "dakto": {
        "adakt": "당황",
        "vl'dakto": "당황한",
        "yl'dakto": "당황하게"
      }
    },
    "saska": {
      "뜻": "절망하다",
      "saska": {
        "asask": "절망",
        "vl'saska": "절망한",
        "yl'saska": "절망하게"
      }
    },
    "suibi": {
      "뜻": "무력하다",
      "suibi": {
        "asuib": "무력",
        "vl'suibi": "무력한",
        "yl'suibi": "무력하게"
      }
    },
    "cluku": {
      "뜻": "신중하다",
      "cluku": {
        "acluk": "신중",
        "vl'cluku": "신중한",
        "yl'cluku": "신중하게"
      }
    },
    "kosce": {
      "뜻": "오만하다",
      "kosce": {
        "akosc": "오만",
        "vl'kosce": "오만한",
        "yl'kosce": "오만하게"
      }
    },
    "sjoco": {
      "뜻": "겸손하다",
      "sjoco": {
        "asjoc": "겸손",
        "vl'sjoco": "겸손한",
        "yl'sjoco": "겸손하게"
      }
    },
    "basja": {
      "뜻": "감사하다",
      "basja": {
        "abasj": "감사",
        "vl'basja": "감사한",
        "yl'basja": "감사하게"
      }
    },
    "maqli": {
      "뜻": "창피하다",
      "maqli": {
        "amaql": "창피",
        "vl'maqli": "창피한",
        "yl'maqli": "창피하게"
      }
    },
    "khasu": {
      "뜻": "공감하다",
      "khasu": {
        "akhas": "공감",
        "vl'khasu": "공감한",
        "yl'khasu": "공감하게"
      }
    },
    "clobe": {
      "뜻": "만족하다",
      "clobe": {
        "aclob": "만족",
        "vl'clobe": "만족한",
        "yl'clobe": "만족하게"
      }
    },
    "kwuco": {
      "뜻": "흥분하다",
      "kwuco": {
        "akwuc": "흥분",
        "vl'kwuco": "흥분한",
        "yl'kwuco": "흥분하게"
      }
    },
    "fkaca": {
      "뜻": "불안하다",
      "fkaca": {
        "afkac": "불안",
        "vl'fkaca": "불안한",
        "yl'fkaca": "불안하게"
      }
    },
    "kifli": {
      "뜻": "일하다",
      "kifli": {
        "akifl": "일",
        "vl'kifli": "일한",
        "yl'kifli": "일하게"
      }
    },
    "kulku": {
      "뜻": "운동하다",
      "kulku": {
        "akulk": "운동",
        "vl'kulku": "운동한",
        "yl'kulku": "운동하게"
      }
    },
    "bloke": {
      "뜻": "전공하다",
      "bloke": {
        "ablok": "전공",
        "vl'bloke": "전공한",
        "yl'bloke": "전공하게"
      }
    },
    "ktabo": {
      "뜻": "입학하다",
      "ktabo": {
        "aktab": "입학",
        "vl'ktabo": "입학한",
        "yl'ktabo": "입학하게"
      }
    },
    "fkega": {
      "뜻": "졸업하다",
      "fkega": {
        "afkeg": "졸업",
        "vl'fkega": "졸업한",
        "yl'fkega": "졸업하게"
      }
    },
    "kieki": {
      "뜻": "번영하다",
      "kieki": {
        "akiek": "번영",
        "vl'kieki": "번영한",
        "yl'kieki": "번영하게"
      }
    },
    "lijnu": {
      "뜻": "지시하다",
      "lijnu": {
        "alijn": "지시",
        "vl'lijnu": "지시한",
        "yl'lijnu": "지시하게"
      }
    },
    "cjebe": {
      "뜻": "분석하다",
      "cjebe": {
        "acjeb": "분석",
        "vl'cjebe": "분석한",
        "yl'cjebe": "분석하게"
      }
    },
    "chido": {
      "뜻": "충돌하다",
      "chido": {
        "achid": "충돌",
        "vl'chido": "충돌한",
        "yl'chido": "충돌하게"
      }
    },
    "kjoka": {
      "뜻": "방송하다",
      "kjoka": {
        "akjok": "방송",
        "vl'kjoka": "방송한",
        "yl'kjoka": "방송하게",
        "elkjok": "방송인"
      }
    },
    "cjoki": {
      "뜻": "운송하다",
      "cjoki": {
        "acjok": "운송",
        "vl'cjoki": "운송한",
        "yl'cjoki": "운송하게"
      }
    },
    "boabu": {
      "뜻": "광고하다",
      "boabu": {
        "aboab": "광고",
        "vl'boabu": "광고한",
        "yl'boabu": "광고하게"
      }
    },
    "cjoke": {
      "뜻": "전송하다",
      "cjoke": {
        "acjok": "전송",
        "vl'cjoke": "전송한",
        "yl'cjoke": "전송하게"
      }
    },
    "fiubo": {
      "뜻": "상륙하다",
      "fiubo": {
        "afiub": "상륙",
        "vl'fiubo": "상륙한",
        "yl'fiubo": "상륙하게"
      }
    },
    "genba": {
      "뜻": "개척하다",
      "genba": {
        "agenb": "개척",
        "vl'genba": "개척한",
        "yl'genba": "개척하게"
      }
    },
    "lepni": {
      "뜻": "재배하다",
      "lepni": {
        "alepn": "재배",
        "vl'lepni": "재배한",
        "yl'lepni": "재배하게"
      }
    },
    "klobu": {
      "뜻": "정복하다",
      "klobu": {
        "aklob": "정복",
        "vl'klobu": "정복한",
        "yl'klobu": "정복하게"
      }
    },
    "jhene": {
      "뜻": "수확하다",
      "jhene": {
        "ajhen": "수확",
        "vl'jhene": "수확한",
        "yl'jhene": "수확하게"
      }
    },
    "bleno": {
      "뜻": "기절하다",
      "bleno": {
        "ablen": "기절",
        "vl'bleno": "기절한",
        "yl'bleno": "기절하게"
      }
    },
    "kjina": {
      "뜻": "응시하다",
      "kjina": {
        "akjin": "응시",
        "vl'kjina": "응시한",
        "yl'kjina": "응시하게"
      }
    },
    "totgi": {
      "뜻": "호흡하다",
      "totgi": {
        "atotg": "호흡",
        "vl'totgi": "호흡한",
        "yl'totgi": "호흡하게"
      }
    },
    "flufu": {
      "뜻": "발굴하다",
      "flufu": {
        "afluf": "발굴",
        "vl'flufu": "발굴한",
        "yl'flufu": "발굴하게"
      }
    },
    "slake": {
      "뜻": "매장하다",
      "slake": {
        "aslak": "매장",
        "vl'slake": "매장한",
        "yl'slake": "매장하게"
      }
    },
    "meklo": {
      "뜻": "청소하다",
      "meklo": {
        "amekl": "청소",
        "vl'meklo": "청소한",
        "yl'meklo": "청소하게"
      }
    },
    "lioba": {
      "뜻": "조직하다",
      "lioba": {
        "aliob": "조직",
        "vl'lioba": "조직한",
        "yl'lioba": "조직하게"
      }
    },
    "bleki": {
      "뜻": "고정하다",
      "bleki": {
        "ablek": "고정",
        "vl'bleki": "고정한",
        "yl'bleki": "고정하게"
      }
    },
    "kictu": {
      "뜻": "연합하다",
      "kictu": {
        "akict": "연합",
        "vl'kictu": "연합한",
        "yl'kictu": "연합하게"
      }
    },
    "gulmo": {
      "뜻": "불공평하다",
      "gulmo": {
        "agulm": "불공평",
        "vl'gulmo": "불공평한",
        "yl'gulmo": "불공평하게"
      }
    },
    "kunla": {
      "뜻": "우세하다",
      "kunla": {
        "akunl": "우세",
        "vl'kunla": "우세한",
        "yl'kunla": "우세하게"
      }
    },
    "cjeki": {
      "뜻": "신성하다",
      "cjeki": {
        "acjek": "신성",
        "vl'cjeki": "신성한",
        "yl'cjeki": "신성하게"
      }
    },
    "kiegu": {
      "뜻": "예배하다",
      "kiegu": {
        "akieg": "예배",
        "vl'kiegu": "예배한",
        "yl'kiegu": "예배하게"
      }
    },
    "ktage": {
      "뜻": "통합하다",
      "ktage": {
        "aktag": "통합",
        "vl'ktage": "통합한",
        "yl'ktage": "통합하게"
      }
    },
    "qioto": {
      "뜻": "표현하다",
      "qioto": {
        "aqiot": "표현",
        "vl'qioto": "표현한",
        "yl'qioto": "표현하게"
      }
    },
    "clina": {
      "뜻": "전시하다",
      "clina": {
        "aclin": "전시",
        "vl'clina": "전시한",
        "yl'clina": "전시하게"
      }
    },
    "gikni": {
      "뜻": "비유하다",
      "gikni": {
        "agikn": "비유",
        "vl'gikni": "비유한",
        "yl'gikni": "비유하게"
      }
    },
    "kiabu": {
      "뜻": "요약하다",
      "kiabu": {
        "akiab": "요약",
        "vl'kiabu": "요약한",
        "yl'kiabu": "요약하게"
      }
    },
    "blabe": {
      "뜻": "작곡하다",
      "blabe": {
        "ablab": "작곡",
        "vl'blabe": "작곡한",
        "yl'blabe": "작곡하게"
      }
    },
    "loabo": {
      "뜻": "조각하다",
      "loabo": {
        "aloab": "조각",
        "vl'loabo": "조각한",
        "yl'loabo": "조각하게"
      }
    },
    "cjefa": {
      "뜻": "건설하다",
      "cjefa": {
        "acjeg": "건설",
        "vl'cjefa": "건설한",
        "yl'cjefa": "건설하게"
      }
    },
    "toibi": {
      "뜻": "계획하다",
      "toibi": {
        "atoib": "계획",
        "vl'toibi": "계획한",
        "yl'toibi": "계획하게"
      }
    },
    "gukbu": {
      "뜻": "붕괴하다",
      "gukbu": {
        "agukb": "붕괴",
        "vl'gukbu": "붕괴한",
        "yl'gukbu": "붕괴하게"
      }
    },
    "sjice": {
      "뜻": "참신하다",
      "sjice": {
        "asjic": "참신",
        "vl'sjice": "참신한",
        "yl'sjice": "참신하게"
      }
    },
    "mifno": {
      "뜻": "치료하다",
      "mifno": {
        "amifn": "치료",
        "vl'mifno": "치료한",
        "yl'mifno": "치료하게"
      }
    },
    "jujfa": {
      "뜻": "수술하다",
      "jujfa": {
        "ajujf": "수술",
        "vl'jujfa": "수술한",
        "yl'jujfa": "수술하게"
      }
    },
    "gmuki": {
      "뜻": "보충하다",
      "gmuki": {
        "agmuk": "보충",
        "vl'gmuki": "보충한",
        "yl'gmuki": "보충하게"
      }
    },
    "masne": {
      "뜻": "참하다",
      "masne": {
        "amasn": "참",
        "vl'masne": "참한",
        "yl'manse": "참하게"
      }
    },
    "meako": {
      "뜻": "처방하다",
      "meako": {
        "ameak": "처방",
        "vl'meako": "처방한",
        "yl'meako": "처방하게"
      }
    },
    "liaca": {
      "뜻": "진단하다",
      "liaca": {
        "aliac": "진단",
        "vl'liaca": "진단한",
        "yl'liaca": "진단하게"
      }
    },
    "togbi": {
      "뜻": "회복하다",
      "togbi": {
        "atogb": "회복",
        "vl'togbi": "회복한",
        "yl'togbi": "회복하게"
      }
    },
    "kiebu": {
      "뜻": "입력하다",
      "kiebu": {
        "akieb": "입력",
        "vl'kiebu": "입력한",
        "yl'kiebu": "입력하게"
      }
    },
    "sieke": {
      "뜻": "발명하다",
      "sieke": {
        "asiek": "발명",
        "vl'sieke": "발명한",
        "yl'sieke": "발명하게"
      }
    },
    "lekto": {
      "뜻": "정화하다",
      "lekto": {
        "alekt": "정화",
        "vl'lekto": "정화한",
        "yl'lekto": "정화하게"
      }
    },
    "jeiba": {
      "뜻": "서식하다",
      "jeiba": {
        "ajeib": "서식",
        "vl'jeiba": "서식한",
        "yl'jeiba": "서식하게"
      }
    },
    "belni": {
      "뜻": "거주하다",
      "belni": {
        "abeln": "거주",
        "vl'belni": "거주한",
        "yl'belni": "거주하게"
      }
    },
    "bacnu": {
      "뜻": "가능하다",
      "bacnu": {
        "abacn": "가능",
        "vl'bacnu": "가능한",
        "yl'bacnu": "가능하게"
      }
    },
    "gloce": {
      "뜻": "보존하다",
      "gloce": {
        "agloc": "보존",
        "vl'gloce": "보존한",
        "yl'gloce": "보존하게"
      }
    },
    "lefto": {
      "뜻": "재활용하다",
      "lefto": {
        "aleft": "재활용",
        "vl'lefto": "재활용한",
        "yl'lefto": "재활용하게"
      }
    },
    "siefa": {
      "뜻": "멸종하다",
      "siefa": {
        "asief": "멸종",
        "vl'siefa": "멸종한",
        "yl'siefa": "멸종하게"
      }
    },
    "qojbi": {
      "뜻": "포식하다",
      "qojbi": {
        "aqojb": "포식",
        "vl'qojbi": "포식한",
        "yl'qojbi": "포식하게"
      }
    },
    "kenlu": {
      "뜻": "약탈하다",
      "kenlu": {
        "akenl": "약탈",
        "vl'kenlu": "약탈한",
        "yl'kenlu": "약탈하게"
      }
    },
    "gulte": {
      "뜻": "부화하다",
      "gulte": {
        "agult": "부화",
        "vl'gulte": "부화한",
        "yl'gulte": "부화하게"
      }
    },
    "boklo": {
      "뜻": "고용하다",
      "boklo": {
        "abokl": "고용",
        "vl'boklo": "고용한",
        "yl'boklo": "고용하게"
      }
    },
    "kwata": {
      "뜻": "항의하다",
      "kwata": {
        "akwat": "항의",
        "vl'kwata": "항의한",
        "yl'kwata": "항의하게"
      }
    },
    "ciefi": {
      "뜻": "환불하다",
      "ciefi": {
        "acief": "환불",
        "vl'ciefi": "환불한",
        "yl'ciefi": "환불하게"
      }
    },
    "damfu": {
      "뜻": "대출하다",
      "damfu": {
        "adamf": "대출",
        "vl'damfu": "대출한",
        "yl'damfu": "대출하게"
      }
    },
    "chese": {
      "뜻": "축소하다",
      "chese": {
        "aches": "축소",
        "vl'chese": "축소한",
        "yl'chese": "축소하게"
      }
    },
    "limfo": {
      "뜻": "지출하다",
      "limfo": {
        "alimf": "지출",
        "vl'limfo": "지출한",
        "yl'limfo": "지출하게"
      }
    },
    "decta": {
      "뜻": "수사하다",
      "decta": {
        "adect": "수사",
        "vl'decta": "수사한",
        "yl'decta": "수사하게"
      }
    },
    "bensi": {
      "뜻": "구매하다",
      "bensi": {
        "abens": "구매",
        "vl'bensi": "구매한",
        "yl'bensi": "구매하게"
      }
    },
    "pultu": {
      "뜻": "투자하다",
      "pultu": {
        "apult": "투자",
        "vl'pultu": "투자한",
        "yl'pultu": "투자하게"
      }
    },
    "solbe": {
      "뜻": "목격하다",
      "solbe": {
        "asolb": "목격",
        "vl'solbe": "목격한",
        "yl'solbe": "목격하게"
      }
    },
    "bioto": {
      "뜻": "교환하다",
      "bioto": {
        "abiot": "교환",
        "vl'bioto": "교환한",
        "yl'bioto": "교환하게"
      }
    },
    "kuiga": {
      "뜻": "위반하다",
      "kuiga": {
        "akuig": "위반",
        "vl'kuiga": "위반한",
        "yl'kuiga": "위반하게"
      }
    },
    "lwesi": {
      "뜻": "광범위하다",
      "lwesi": {
        "alwes": "광범위",
        "vl'lwesi": "광범위한",
        "yl'lwesi": "광범위하게"
      }
    },
    "polmu": {
      "뜻": "폭로하다",
      "polmu": {
        "apolm": "폭로",
        "vl'polmu": "폭로한",
        "yl'polmu": "폭로하게"
      }
    },
    "lwube": {
      "뜻": "증가하다",
      "lwube": {
        "alwub": "증가",
        "vl'lwube": "증가한",
        "yl'lwube": "증가하게"
      }
    },
    "bajso": {
      "뜻": "감소하다",
      "bajso": {
        "abajs": "감소",
        "vl'bajso": "감소한",
        "yl'bajso": "감소하게"
      }
    },
    "lenpa": {
      "뜻": "공급하다",
      "lenpa": {
        "alenp": "공급",
        "vl'lenpa": "공급한",
        "yl'lenpa": "공급하게"
      }
    },
    "gursi": {
      "뜻": "분명하다",
      "gursi": {
        "agurs": "분명",
        "vl'gursi": "분명한",
        "yl'gursi": "분명하게"
      }
    },
    "sontu": {
      "뜻": "모호하다",
      "sontu": {
        "asont": "모호",
        "vl'sontu": "모호한",
        "yl'sontu": "모호하게"
      }
    },
    "kunte": {
      "뜻": "계속하다",
      "kunte": {
        "akunt": "계속",
        "vl'kunte": "계속한",
        "yl'kunte": "계속하게"
      }
    },
    "jasco": {
      "뜻": "산만하다",
      "jasco": {
        "ajasc": "산만",
        "vl'jasco": "산만한",
        "yl'jasco": "산만하게"
      }
    },
    "pajka": {
      "뜻": "탑승하다",
      "pajka": {
        "apajk": "탑승",
        "vl'pajka": "탑승한",
        "yl'pajka": "탑승하게"
      }
    },
    "maipi": {
      "뜻": "채택하다",
      "maipi": {
        "amaip": "채택",
        "vl'maipi": "채택한",
        "yl'maipi": "채택하게"
      }
    },
    "munbu": {
      "뜻": "추가하다",
      "munbu": {
        "amunb": "추가",
        "vl'munbu": "추가한",
        "yl'munbu": "추가하게"
      }
    },
    "sorke": {
      "뜻": "문의하다",
      "sorke": {
        "asork": "문의",
        "vl'sorke": "문의한",
        "yl'sorke": "문의하게"
      }
    },
    "gajno": {
      "뜻": "발생하다",
      "gajno": {
        "agajn": "발생",
        "vl'gajno": "발생한",
        "yl'gajno": "발생하게"
      }
    },
    "kiuga": {
      "뜻": "유발하다",
      "kiuga": {
        "akiug": "유발",
        "vl'kiuga": "유발한",
        "yl'kiuga": "유발하게"
      }
    },
    "kmaki": {
      "뜻": "팽창하다",
      "kmaki": {
        "akmak": "팽창",
        "vl'kmaki": "팽창한",
        "yl'kmaki": "팽창하게"
      }
    },
    "jandu": {
      "뜻": "상당하다",
      "jandu": {
        "ajand": "상당",
        "vl'jandu": "상당한",
        "yl'jandu": "상당하게"
      }
    },
    "gufne": {
      "뜻": "분류하다",
      "gufne": {
        "agufn": "분류",
        "vl'gufne": "분류한",
        "yl'gufne": "분류하게"
      }
    },
    "gaklo": {
      "뜻": "방어하다",
      "gaklo": {
        "agakl": "방어",
        "vl'gaklo": "방어한",
        "yl'gaklo": "방어하게"
      }
    },
    "kwila": {
      "뜻": "의존하다",
      "kwila": {
        "akwil": "의존",
        "vl'kwila": "의존한",
        "yl'kwila": "의존하게"
      }
    },
    "dambi": {
      "뜻": "도착하다",
      "dambi": {
        "adamb": "도착",
        "vl'dambi": "도착한",
        "yl'dambi": "도착하게"
      }
    },
    "lancu": {
      "뜻": "잔인하다",
      "lancu": {
        "alanc": "잔인",
        "vl'lancu": "잔인한",
        "yl'lancu": "잔인하게"
      }
    },
    "mufte": {
      "뜻": "출현하다",
      "mufte": {
        "amuft": "출현",
        "vl'mufte": "출현한",
        "yl'mufte": "출현하게"
      }
    },
    "bikno": {
      "뜻": "기여하다",
      "bikno": {
        "abikn": "기여",
        "vl'bikno": "기여한",
        "yl'bikno": "기여하게"
      }
    },
    "kurna": {
      "뜻": "분배하다",
      "kurna": {
        "akurn": "분배",
        "vl'kurna": "분배한",
        "yl'kurna": "분배하게"
      }
    },
    "boadi": {
      "뜻": "관대하다",
      "boadi": {
        "aboad": "관대",
        "vl'boadi": "관대한",
        "yl'boadi": "관대하게"
      }
    },
    "dailu": {
      "뜻": "대접하다",
      "dailu": {
        "adail": "대접",
        "vl'dailu": "대접한",
        "yl'dailu": "대접하게"
      }
    },
    "jiabe": {
      "뜻": "시작하다",
      "jiabe": {
        "ajiab": "시작",
        "vl'jiabe": "시작한",
        "yl'jiabe": "시작하게"
      }
    },
    "linto": {
      "뜻": "진화하다",
      "linto": {
        "alint": "진화",
        "vl'linto": "진화한",
        "yl'linto": "진화하게"
      }
    },
    "hwata": {
      "뜻": "상승하다",
      "hwata": {
        "ahwat": "상승",
        "vl'hwata": "상승한",
        "yl'hwata": "상승하게"
      }
    },
    "mujfi": {
      "뜻": "충실하다",
      "mujfi": {
        "amujf": "충실",
        "vl'mujfi": "충실한",
        "yl'mujfi": "충실하게"
      }
    },
    "bojnu": {
      "뜻": "공손하다",
      "bojnu": {
        "abojn": "공손",
        "vl'bojnu": "공손한",
        "yl'bojnu": "공손하게"
      }
    },
    "kesce": {
      "뜻": "예민하다",
      "kesce": {
        "akesc": "예민",
        "vl'kesce": "예민한",
        "yl'kesce": "예민하게"
      }
    },
    "dabno": {
      "뜻": "딱딱하다",
      "dabno": {
        "adabn": "딱딱",
        "vl'dabno": "딱딱한",
        "yl'dabno": "딱딱하게"
      }
    },
    "kecla": {
      "뜻": "인용하다",
      "kecla": {
        "akecl": "인용",
        "vl'kecla": "인용한",
        "yl'kecla": "인용하게"
      }
    },
    "jerki": {
      "뜻": "성공하다",
      "jerki": {
        "ajerk": "성공",
        "vl'jerki": "성공한",
        "yl'jerki": "성공하게"
      }
    },
    "tonfu": {
      "뜻": "끔찍하다",
      "tonfu": {
        "atonf": "끔찍",
        "vl'tonfu": "끔찍한",
        "yl'tonfu": "끔찍하게"
      }
    },
    "dakne": {
      "뜻": "다양하다",
      "dakne": {
        "adakn": "다양",
        "vl'dakne": "다양한",
        "yl'dakne": "다양하게"
      }
    },
    "galto": {
      "뜻": "배회하다",
      "galto": {
        "agalt": "배회",
        "vl'galto": "배회한",
        "yl'galto": "배회하게"
      }
    },
    "lomca": {
      "뜻": "조언하다",
      "lomca": {
        "alomc": "조언",
        "vl'lomca": "조언한",
        "yl'lomca": "조언하게"
      }
    },
    "bansi": {
      "뜻": "가난하다",
      "bansi": {
        "abans": "가난",
        "vl'bansi": "가난한",
        "yl'bansi": "가난하게"
      }
    },
    "bejcu": {
      "뜻": "계산하다",
      "bejcu": {
        "abejc": "계산",
        "vl'bejcu": "계산한",
        "yl'bejcu": "계산하게"
      }
    },
    "kiofe": {
      "뜻": "요리하다",
      "kiofe": {
        "akiof": "요리",
        "vl'kiofe": "요리한",
        "yl'kiofe": "요리하게"
      }
    },
    "basno": {
      "뜻": "갈망하다",
      "basno": {
        "abasn": "갈망",
        "vl'basno": "갈망한",
        "yl'basno": "갈망하게"
      }
    },
    "biefa": {
      "뜻": "격려하다",
      "biefa": {
        "abief": "격려",
        "vl'biefa": "격려한",
        "yl'biefa": "격려하게"
      }
    },
    "malti": {
      "뜻": "차지하다",
      "malti": {
        "amalt": "차지",
        "vl'malti": "차지한",
        "yl'malti": "차지하게"
      }
    },
    "bjifu": {
      "뜻": "확실하다",
      "bjifu": {
        "abjif": "확실",
        "vl'bjifu": "확실한",
        "yl'bjifu": "확실하게"
      }
    },
    "laice": {
      "뜻": "재판하다",
      "laice": {
        "alaic": "재판",
        "vl'laice": "재판한",
        "yl'laice": "재판하게"
      }
    },
    "leklo": {
      "뜻": "저장하다",
      "leklo": {
        "alekl": "저장",
        "vl'leklo": "저장한",
        "yl'leklo": "저장하게"
      }
    },
    "gajna": {
      "뜻": "반사하다",
      "gajna": {
        "agajn": "반사",
        "vl'gajna": "반사한",
        "yl'gajna": "반사하게"
      }
    },
    "cheki": {
      "뜻": "생각하다",
      "cheki": {
        "achek": "생각",
        "vl'cheki": "생각한",
        "yl'cheki": "생각하게"
      }
    },
    "ludnu": {
      "뜻": "주도하다",
      "ludnu": {
        "aludn": "주도",
        "vl'ludnu": "주도한",
        "yl'ludnu": "주도하게"
      }
    },
    "batne": {
      "뜻": "판단하다",
      "batne": {
        "abatn": "판단",
        "vl'batne": "판단한",
        "yl'batne": "판단하게"
      }
    },
    "stuto": {
      "뜻": "명령하다",
      "stuto": {
        "astut": "명령",
        "vl'stuto": "명령한",
        "yl'stuto": "명령하게"
      }
    },
    "lusca": {
      "뜻": "주문하다",
      "lusca": {
        "alusc": "주문",
        "vl'lusca": "주문한",
        "yl'lusca": "주문하게"
      }
    },
    "ledci": {
      "뜻": "정돈하다",
      "ledci": {
        "aledc": "정돈",
        "vl'ledci": "정돈한",
        "yl'ledci": "정돈하게"
      }
    },
    "mufcu": {
      "뜻": "추론하다",
      "mufcu": {
        "amufc": "추론",
        "vl'mufcu": "추론한",
        "yl'mufcu": "추론하게"
      }
    },
    "befte": {
      "뜻": "거래하다",
      "befte": {
        "abeft": "거래",
        "vl'befte": "거래한",
        "yl'befte": "거래하게"
      }
    },
    "jonbo": {
      "뜻": "소박하다",
      "jonbo": {
        "ajonb": "소박",
        "vl'jonbo": "소박한",
        "yl'jonbo": "소박하게"
      }
    },
    "leima": {
      "뜻": "제출하다",
      "leima": {
        "aleim": "제출",
        "vl'leima": "제출한",
        "yl'leima": "제출하게"
      }
    },
    "bloki": {
      "뜻": "복종하다",
      "bloki": {
        "ablok": "복종",
        "vl'bloki": "복종한",
        "yl'bloki": "복종하게"
      }
    },
    "qieku": {
      "뜻": "평평하다",
      "qieku": {
        "aqiek": "평평",
        "vl'qieku": "평평한",
        "yl'qieku": "평평하게",
        "mqiek": "평지"
      }
    },
    "kufle": {
      "뜻": "울퉁불퉁하다",
      "kufle": {
        "akufl": "울퉁불퉁",
        "vl'kufle": "울퉁불퉁한",
        "yl'kufle": "울퉁불퉁하게"
      }
    },
    "saico": {
      "뜻": "매끈하다",
      "saico": {
        "asaic": "매끈",
        "vl'saico": "매끈한",
        "yl'saico": "매끈하게"
      }
    },
    "jeaka": {
      "뜻": "석방하다",
      "jeaka": {
        "ajeak": "석방",
        "vl'jeaka": "석방한",
        "yl'jeaka": "석방하게"
      }
    },
    "kmufi": {
      "뜻": "방출하다",
      "kmufi": {
        "akmuf": "방출",
        "vl'kmufi": "방출한",
        "yl'kmufi": "방출하게"
      }
    },
    "kjelu": {
      "뜻": "맹세하다",
      "kjelu": {
        "akjel": "맹세",
        "vl'kjelu": "맹세한",
        "yl'kjelu": "맹세하게"
      }
    },
    "qieke": {
      "뜻": "공평하다",
      "qieke": {
        "aqiek": "공평",
        "vl'qieke": "공평한",
        "yl'qieke": "공평하게"
      }
    },
    "cmafo": {
      "뜻": "관찰하다",
      "cmafo": {
        "acmaf": "관찰",
        "vl'cmafo": "관찰한",
        "yl'cmafo": "관찰하게"
      }
    },
    "jukna": {
      "뜻": "수여하다",
      "jukna": {
        "ajukn": "수여",
        "vl'jukna": "수여한",
        "yl'jukna": "수여하게"
      }
    },
    "bojli": {
      "뜻": "고소하다",
      "bojli": {
        "abojl": "고소",
        "vl'bojli": "고소한",
        "yl'bojli": "고소하게"
      }
    },
    "bjafu": {
      "뜻": "묵살하다",
      "bjafu": {
        "abjaf": "묵살",
        "vl'bjafu": "묵살한",
        "yl'bjafu": "묵살하게"
      }
    },
    "taibe": {
      "뜻": "해고하다",
      "taibe": {
        "ataib": "해고",
        "vl'taibe": "해고한",
        "yl'taibje": "해고하게"
      }
    },
    "tjaco": {
      "뜻": "해산하다",
      "tjaco": {
        "atjac": "해산",
        "vl'tjaco": "해산한",
        "yl'tjaco": "해산하게"
      }
    },
    "paika": {
      "뜻": "지탱하다",
      "paika": {
        "apaik": "지탱",
        "vl'paika": "지탱한",
        "yl'paika": "지탱하게"
      }
    },
    "kiefi": {
      "뜻": "배열하다",
      "kiefi": {
        "akief": "배열",
        "vl'kiefi": "배열한",
        "yl'kiefi": "배열하게"
      }
    },
    "jijnu": {
      "뜻": "실시하다",
      "jijnu": {
        "ajijn": "실시",
        "vl'jijnu": "실시한",
        "yl'jijnu": "실시하게"
      }
    },
    "litme": {
      "뜻": "지휘하다",
      "litme": {
        "alitm": "지휘",
        "vl'litme": "지휘한",
        "yl'litme": "지휘하게"
      }
    },
    "madco": {
      "뜻": "차단하다",
      "madco": {
        "amadc": "차단",
        "vl'madco": "차단한",
        "yl'madco": "차단하게"
      }
    },
    "balka": {
      "뜻": "건강하다",
      "balka": {
        "abalk": "건강",
        "vl'balka": "건강한",
        "yl'balka": "건강하게"
      }
    },
    "besti": {
      "뜻": "검열하다",
      "besti": {
        "abest": "검열",
        "vl'besti": "검열한",
        "yl'besti": "검열하게"
      }
    },
    "kejfu": {
      "뜻": "연설하다",
      "kejfu": {
        "akejf": "연설",
        "vl'kejfu": "연설한",
        "yl'kejfu": "연설하게"
      }
    },
    "jesfe": {
      "뜻": "선물하다",
      "jesfe": {
        "ajesf": "선물",
        "vl'jesfe": "선물한",
        "yl'jesfe": "선물하게"
      }
    },
    "jumbo": {
      "뜻": "수축하다",
      "jumbo": {
        "ajumb": "수축",
        "vl'jumbo": "수축한",
        "yl'jumbo": "수축하게"
      }
    },
    "chaca": {
      "뜻": "단단하다",
      "chaca": {
        "achac": "단단",
        "vl'chaca": "단단한",
        "yl'chaci": "단단하게"
      }
    },
    "pwuci": {
      "뜻": "튼튼하다",
      "pwuci": {
        "vl'pwuci": "튼튼한",
        "yl'pwuci": "튼튼하게"
      }
    },
    "kleku": {
      "뜻": "냉정하다",
      "kleku": {
        "aklek": "냉정",
        "vl'kleku": "냉정한",
        "yl'kleku": "냉정하게"
      }
    },
    "kisbe": {
      "뜻": "임기하다",
      "kisbe": {
        "akisb": "임기",
        "vl'kisbe": "임기한",
        "yl'kisbe": "임기하게"
      }
    },
    "tufno": {
      "뜻": "훈련하다",
      "tufno": {
        "atufn": "훈련",
        "vl'tufno": "훈련한",
        "yl'tufno": "훈련하게"
      }
    },
    "jicma": {
      "뜻": "신청하다",
      "jicma": {
        "ajicm": "신청",
        "vl'jicma": "신청한",
        "yl'jicma": "신청하게"
      }
    },
    "blagi": {
      "뜻": "복잡하다",
      "blagi": {
        "ablag": "복잡",
        "vl'blagi": "복잡한",
        "yl'blagi": "복잡하게"
      }
    },
    "mufju": {
      "뜻": "출시하다",
      "mufju": {
        "amufj": "출시",
        "vl'mufju": "출시한",
        "yl'mufju": "출시하게"
      }
    },
    "bokle": {
      "뜻": "관여하다",
      "bokle": {
        "abokle": "관여",
        "vl'bokle": "관여한",
        "yl'bokle": "관여하게"
      }
    },
    "biclo": {
      "뜻": "기능하다",
      "biclo": {
        "abiclo": "기능",
        "vl'biclo": "기능한",
        "yl'biclo": "기능하게"
      }
    },
    "jifna": {
      "뜻": "실수하다",
      "jifna": {
        "ajifn": "실수",
        "vl'jifna": "실수한",
        "yl'jifna": "실수하게"
      }
    },
    "burki": {
      "뜻": "급여하다",
      "burki": {
        "aburk": "급여",
        "vl'burki": "급여한",
        "yl'burki": "급여하게"
      }
    },
    "batnu": {
      "뜻": "가해하다",
      "batnu": {
        "abatn": "가해",
        "vl'batnu": "가해한",
        "yl'batnu": "가해하게"
      }
    },
    "bidne": {
      "뜻": "기도하다",
      "bidne": {
        "abidn": "기도",
        "vl'bidne": "기도한",
        "yl'bidne": "기도하게"
      }
    },
    "bjubo": {
      "뜻": "익숙하다",
      "bjubo": {
        "abjub": "익숙",
        "vl'bjubo": "익숙한",
        "yl'bjubo": "익숙하게"
      }
    },
    "ftesa": {
      "뜻": "실험하다",
      "ftesa": {
        "aftes": "실험",
        "vl'ftesa": "실험한",
        "yl'ftesa": "실험하게"
      }
    },
    "jidni": {
      "뜻": "시도하다",
      "jidni": {
        "ajidn": "시도",
        "vl'jidni": "시도한",
        "yl'jidni": "시도하게"
      }
    },
    "daifu": {
      "뜻": "대립하다",
      "daifi": {
        "adaif": "대립",
        "vl'daifu": "대립한",
        "yl'daifu": "대립하게"
      }
    },
    "jalke": {
      "뜻": "손상하다",
      "jalke": {
        "ajalk": "손상",
        "vl'jalke": "손상한",
        "yl'jalke": "손상하게"
      }
    },
    "golko": {
      "뜻": "보증하다",
      "golko": {
        "agolk": "보증",
        "vl'golko": "보증한",
        "yl'golko": "보증하게"
      }
    },
    "jikna": {
      "뜻": "시위하다",
      "jikna": {
        "ajikn": "시위",
        "vl'jikna": "시위한",
        "yl'jikna": "시위하게"
      }
    },
    "gaimi": {
      "뜻": "배출하다",
      "gaimi": {
        "agaim": "배출",
        "vl'gaimi": "배출한",
        "yl'gaimi": "배출하게"
      }
    },
    "tiecu": {
      "뜻": "혁신하다",
      "tiecu": {
        "atiec": "혁신",
        "vl'tiecu": "혁신한",
        "yl'tiecu": "혁신하게"
      }
    },
    "pedbe": {
      "뜻": "터득하다",
      "pedbe": {
        "apedb": "터득",
        "vl'pedbe": "터득한",
        "yl'pedbe": "터득하게"
      }
    },
    "kablo": {
      "뜻": "이야기하다",
      "kablo": {
        "akabl": "이야기",
        "vl'kablo": "이야기한",
        "yl'kablo": "이야기하게"
      }
    },
    "cetna": {
      "뜻": "근거하다",
      "cetna": {
        "acetn": "근거",
        "vl'cetna": "근거한",
        "yl'cetna": "근거하게"
      }
    },
    "jicti": {
      "뜻": "신호하다",
      "jicti": {
        "ajict": "신호",
        "vl'jicti": "신호한",
        "yl'jicti": "신호하게"
      }
    },
    "kuelu": {
      "뜻": "애원하다",
      "kuelu": {
        "akuel": "애원",
        "vl'kuelu": "애원한",
        "yl'kuelu": "애원하게"
      }
    },
    "bikne": {
      "뜻": "기원하다",
      "bikne": {
        "abikn": "기원",
        "vl'bikne": "기원한",
        "yl'bikne": "기원하게"
      }
    },
    "bifgo": {
      "뜻": "결핍하다",
      "bifgo": {
        "abifg": "결핍",
        "vl'bifgo": "결핍한",
        "yl'bifgo": "결핍하게"
      }
    },
    "golka": {
      "뜻": "보장하다",
      "golka": {
        "agolk": "보장",
        "vl'golka": "보장한",
        "yl'golka": "보장하게"
      }
    },
    "fiebi": {
      "뜻": "노력하다",
      "fiebi": {
        "afieb": "노력",
        "vl'fiebi": "노력한",
        "yl'fiebi": "노력하게"
      }
    },
    "bjecu": {
      "뜻": "개선하다",
      "bjecu": {
        "abjec": "개선",
        "vl'bjecu": "개선한",
        "yl'bjecu": "개선하게"
      }
    },
    "tiebe": {
      "뜻": "개혁하다",
      "tiebe": {
        "atieb": "개혁",
        "vl'tiebe": "개혁한",
        "yl'tiebe": "개혁하게"
      }
    },
    "kulfo": {
      "뜻": "우려하다",
      "kulfo": {
        "akulf": "우려",
        "vl'kulfo": "우려한",
        "yl'kulfo": "우려하게"
      }
    },
    "leska": {
      "뜻": "점령하다",
      "leska": {
        "alesk": "점령",
        "vl'leska": "점령한",
        "yl'leska": "점령하게"
      }
    },
    "sqini": {
      "뜻": "목표하다",
      "sqini": {
        "asqin": "목표",
        "vl'sqini": "목표한",
        "yl'sqini": "목표하게"
      }
    },
    "kidku": {
      "뜻": "이동하다",
      "kidku": {
        "akidk": "이동",
        "vl'kidku": "이동한",
        "yl'kidku": "이동하게"
      }
    },
    "biofe": {
      "뜻": "교류하다",
      "biofe": {
        "abiof": "교류",
        "vl'biofe": "교류한",
        "yl'biofe": "교류하게"
      }
    },
    "mango": {
      "뜻": "통찰하다",
      "mango": {
        "amang": "통찰",
        "vl'mango": "통찰한",
        "yl'mango": "통찰하게"
      }
    },
    "thica": {
      "뜻": "할인하다",
      "thica": {
        "athic": "할인",
        "vl'thica": "할인한",
        "yl'thica": "할인하게"
      }
    },
    "floci": {
      "뜻": "토론하다",
      "floci": {
        "afloc": "토론",
        "vl'floci": "토론한",
        "yl'floci": "토론하게"
      }
    },
    "lomtu": {
      "뜻": "조치하다",
      "lomtu": {
        "alomt": "조치",
        "vl'lomtu": "조치한",
        "yl'lomtu": "조치하게"
      }
    },
    "kijbe": {
      "뜻": "연속하다",
      "kijbe": {
        "akijb": "연속",
        "vl'kijbe": "연속한",
        "yl'kijbe": "연속하게"
      }
    },
    "dlaso": {
      "뜻": "부담하다",
      "dlaso": {
        "adlas": "부담",
        "vl'dlaso": "부담한",
        "yl'dlaso": "부담하게"
      }
    },
    "jivla": {
      "뜻": "시원하다",
      "jivla": {
        "ajivl": "시원",
        "vl'jivla": "시원한",
        "yl'jivla": "시원하게"
      }
    },
    "jempi": {
      "뜻": "간단하다",
      "jempi": {
        "ajemp": "간단",
        "vl'jempi": "간단한",
        "yl'jempi": "간단하게"
      }
    },
    "dotbu": {
      "뜻": "똑똑하다",
      "dotbu": {
        "vl'dotbu": "똑똑한",
        "yl'dotbu": "똑똑하게"
      }
    },
    "tivle": {
      "뜻": "활동하다",
      "tivle": {
        "ativl": "활동",
        "vl'tivle": "활동한",
        "yl'tivle": "활동하게"
      }
    },
    "tesko": {
      "뜻": "혐오하다",
      "tesko": {
        "atesk": "혐오",
        "vl'tesko": "혐오한",
        "yl'tesko": "혐오하게"
      }
    },
    "gucla": {
      "뜻": "분노하다",
      "gucla": {
        "agucl": "분노",
        "vl'gucla": "분노한",
        "yl'gucla": "분노하게"
      }
    },
    "talbi": {
      "뜻": "행복하다",
      "talbi": {
        "atalb": "행복",
        "vl'talbi": "행복한",
        "yl'talbi": "행복하게"
      }
    },
    "kimtu": {
      "뜻": "양치하다",
      "kimtu": {
        "akimt": "양치",
        "vl'kimtu": "양치한",
        "yl'kimtu": "양치하게"
      }
    },
    "linpe": {
      "뜻": "질투하다",
      "linpe": {
        "alinp": "질투",
        "vl'linpe": "질투한",
        "yl'linpe": "질투하게"
      }
    },
    "cadfo": {
      "뜻": "전달하다",
      "cadfo": {
        "acadf": "전달",
        "vl'cadfo": "전달한",
        "yl'cadfo": "전달하게"
      }
    },
    "kwisa": {
      "뜻": "의심하다",
      "kwisa": {
        "akwis": "의심",
        "vl'kwisa": "의심한",
        "yl'kwisa": "의심하게"
      }
    },
    "kiudi": {
      "뜻": "유도하다",
      "kiudi": {
        "akiud": "유도",
        "vl'kiudi": "유도한",
        "yl'kiudi": "유도하게"
      }
    },
    "klamu": {
      "뜻": "위장하다",
      "klamu": {
        "aklam": "위장",
        "vl'klamu": "위장한",
        "yl'klamu": "위장하게"
      }
    },
    "kwace": {
      "뜻": "운반하다",
      "kwace": {
        "akwac": "운반",
        "vl'kwace": "운반한",
        "yl'kwace": "운반하게"
      }
    },
    "kiojo": {
      "뜻": "용서하다",
      "kiojo": {
        "akiojo": "용서",
        "vl'kiojo": "용서한",
        "yl'kiojo": "용서하게"
      }
    },
    "jeima": {
      "뜻": "세척하다",
      "jeima": {
        "ajeim": "세척",
        "vl'jeima": "세척한",
        "yl'jeima": "세척하게"
      }
    },
    "jafki": {
      "뜻": "사랑하다",
      "jafki": {
        "ajafk": "사랑",
        "vl'jafki": "사랑한",
        "yl'jafki": "사랑하게"
      }
    },
    "cetnu": {
      "뜻": "복용하다",
      "cetnu": {
        "acetn": "복용",
        "vl'cetnu": "복용한",
        "yl'cetnu": "복용하게"
      }
    },
    "glome": {
      "뜻": "보조하다",
      "glome": {
        "aglom": "보조",
        "vl'glome": "보조한",
        "yl'glome": "보조하게"
      }
    },
    "gadfo": {
      "뜻": "도발하다",
      "gadfo": {
        "agadf": "도발",
        "vl'gadfo": "도발한",
        "yl'gadfo": "도발하게"
      }
    },
    "daida": {
      "뜻": "대답하다",
      "daida": {
        "adaid": "대답",
        "vl'daida": "대답한",
        "yl'daida": "대답하게"
      }
    },
    "cokji": {
      "뜻": "농사하다",
      "cokji": {
        "acokj": "농사",
        "vl'cokji": "농사한",
        "yl'cokji": "농사하게"
      }
    },
    "tketu": {
      "뜻": "공격하다",
      "tketu": {
        "atket": "공격",
        "vl'tketu": "공격한",
        "yl'tketu": "공격하게"
      }
    },
    "benge": {
      "뜻": "공부하다",
      "benge": {
        "abeng": "공부",
        "vl'benge": "공부한",
        "yl'benge": "공부하게"
      }
    },
    "fleko": {
      "뜻": "결정하다",
      "fleko": {
        "aflek": "결정",
        "vl'fleko": "결정한",
        "yl'fleko": "결정하게"
      }
    },
    "qaifa": {
      "뜻": "팔다",
      "qaifa": {
        "vl'qaifa": "판",
        "yl'qaifa": "팔게",
        "mqaif": "상점"
      }
    },
    "twefi": {
      "뜻": "흐르다",
      "twefi": {
        "vl'twefi": "흐른",
        "yl'twefi": "흐르게"
      }
    },
    "puibu": {
      "뜻": "튀기다",
      "puibu": {
        "vl'puibu": "튀긴",
        "yl'puibu": "튀기게"
      }
    },
    "daife": {
      "뜻": "때리다",
      "daife": {
        "vl'daife": "때린",
        "yl'daife": "때리게"
      }
    },
    "malvo": {
      "뜻": "차다",
      "malvo": {
        "vl'malvo": "찬",
        "yl'malvo": "차게"
      }
    },
    "kilna": {
      "뜻": "잊다",
      "kilna": {
        "vl'kilna": "잊은",
        "yl'kilna": "잊게"
      }
    },
    "kguli": {
      "뜻": "울부짖다",
      "kguli": {
        "vl'kguli": "울부짖은",
        "yl'kguli": "울부짖게"
      }
    },
    "kefnu": {
      "뜻": "얼리다",
      "kefnu": {
        "vl'kefnu": "얼린",
        "yl'kefnu": "얼리게"
      }
    },
    "lenbe": {
      "뜻": "적다",
      "lenbe": {
        "vl'lenbe": "적은",
        "yl'lenbe": "적게"
      }
    },
    "sijle": {
      "뜻": "미소 짓다",
      "sijle": {
        "asijl": "미소",
        "vl'sijle": "미소 짓는",
        "yl'sijle": "미소 짓게"
      }
    },
    "sujgu": {
      "뜻": "무섭다",
      "sujgu": {
        "asujg": "공포",
        "vl'sujgu": "무섭운",
        "yl'sujgu": "무섭게"
      }
    },
    "hiele": {
      "뜻": "느끼다",
      "hiele": {
        "vl'hiele": "느낀",
        "yl'hiele": "느끼게"
      }
    },
    "coblu": {
      "뜻": "녹이다",
      "coblu": {
        "vl'coblu": "녹인",
        "yl'coblu": "녹이게"
      }
    },
    "mugna": {
      "뜻": "춥다",
      "mugna": {
        "vl'mugna": "춥운",
        "yl'mugna": "춥게"
      }
    },
    "lafge": {
      "뜻": "짧다",
      "lafge": {
        "vl'lafge": "짧은",
        "yl'lafge": "짧게"
      }
    },
    "lotnu": {
      "뜻": "좋다",
      "lotnu": {
        "vl'lotnu": "좋은",
        "yl'lotnu": "좋게"
      }
    },
    "fiegi": {
      "뜻": "어렵다",
      "fiegi": {
        "vl'fiegi": "어려운",
        "yl'fiegi": "어렵게"
      }
    },
    "twibe": {
      "뜻": "희귀하다",
      "twibe": {
        "atwib": "희귀",
        "vl'twibe": "희귀한",
        "yl'twibe": "희귀하게"
      }
    },
    "lenla": {
      "뜻": "수용하다/받아들이다",
      "lenla": {
        "alenl": "수용",
        "vl'lenla": "수용한/받아들인",
        "yl'lenla": "수용하게/받아들이게"
      }
    }
  }
}
